Workbook

Sheet Dashboard
A1: Operational Data Analysis Dashboard
A2: Excel workbook | Dataset: Olist Brazilian E-Commerce Public Dataset | Analysis focus: delivery performance, delay patterns, and process improvement | R2: Month | S2: Delay Rate (%) | T2: State | U2: Delay Rate (%) | V2: Category | W2: Delay Rate (%) | X2: Status | Y2: Orders
R3: 2016-10 | S3: 1.1320755 | T3: SP | U3: 5.8947004 | V3: Audio | W3: 13.081395 | X3: On Time | Y3: 88644
A4: Total Delivered Orders | B4: =SUM(Monthly_Analysis!B4:B26) -> 96470 | C4: Delay Rate | D4: =SUM(Monthly_Analysis!D4:D26)/SUM(Monthly_Analysis!B4:B26) -> 0.081123665 | E4: Avg Delivery Days | F4: =SUMPRODUCT(Monthly_Analysis!B4:B26,Monthly_Analysis!F4:F26)/SUM(Monthly_Analysis!B4:B26) -> 12.558217 | G4: Avg Review Score | H4: =AVERAGE(Monthly_Analysis!H4:H26) -> 4.0652973 | R4: 2017-01 | S4: 3.0666667 | T4: RJ | U4: 13.473684 | V4: Books Technical | W4: 10.980392 | X4: Delayed | Y4: 7826
R5: 2017-02 | S5: 3.2062916 | T5: MG | U5: 5.6103576 | V5: Home Confort | W5: 10.354223
R6: 2017-03 | S6: 5.5773763 | T6: BA | U6: 14.035627 | V6: Food | W6: 10.091743
A7: Delayed Orders | B7: =SUM(Monthly_Analysis!D4:D26) -> 7826 | C7: On-Time Orders | D7: =SUM(Monthly_Analysis!C4:C26) -> 88644 | E7: Avg Delay Days | F7: =SUMPRODUCT(Monthly_Analysis!B4:B26,Monthly_Analysis!G4:G26)/SUM(Monthly_Analysis!B4:B26) -> 0.77487507 | G7: Avg Freight Cost | H7: =SUMPRODUCT(Monthly_Analysis!B4:B26,Monthly_Analysis!I4:I26)/SUM(Monthly_Analysis!B4:B26) -> 22.785798 | R7: 2017-04 | S7: 7.8593139 | T7: RS | U7: 7.1482036 | V7: Electronics | W7: 9.8524132
R8: 2017-05 | S8: 3.6107193 | T8: SC | U8: 9.7574732 | V8: Baby | W8: 9.3342981
R9: 2017-06 | S9: 3.8596491 | T9: PR | U9: 4.9969531 | V9: Office Furniture | W9: 9.2295345
A10: Key Finding | B10: Evidence from analysis | C10: Operational impact | D10: Suggested action | R10: 2017-07 | S10: 3.4349174 | T10: ES | U10: 12.230576 | V10: Construction Tools Construction | W10: 9.215956
A11: Delay risk is concentrated in specific states. | B11: Overall delay rate is approximately 8.1%, with RJ and BA showing higher delay rates than SP and MG. | C11: Delays are not evenly distributed, so a general fix would be less effective. | D11: Prioritize state-level delivery monitoring and route exception reviews. | R11: 2017-08 | S11: 3.3150489 | T11: CE | U11: 15.324472 | V11: Construction Tools Lights | W11: 9.0517241
A12: Long-distance/last-mile phases appear to drive many late orders. | B12: States with longer average delivery days also show weaker review scores and higher delay rates. | C12: Customer satisfaction may fall when delivery dates are missed. | D12: Create weekly delay dashboards and escalation triggers. | R12: 2017-09 | S12: 5.2048193 | T12: PE | U12: 10.797238 | V12: Health Beauty | W12: 8.989547
A13: Some product categories have higher delay rates. | B13: Audio, Home Comfort, Electronics, and Food show elevated delay rates among categories with meaningful volume. | C13: Category handling, packaging, or carrier requirements may create bottlenecks. | D13: Review category-specific packing standards, supplier readiness, and carrier SLAs. | R13: 2017-10 | S13: 5.2925413
A14: Review scores can be used as an operational quality signal. | B14: Lower review scores are more visible in areas with higher delay rates. | C14: Operations issues may become customer experience issues quickly. | D14: Track review score alongside delivery KPIs, not only sales/order volume. | R14: 2017-11 | S14: 14.311196
R15: 2017-12 | S15: 8.3801923
R16: 2018-01 | S16: 6.5638704
R17: 2018-02 | S17: 15.987796
R18: 2018-03 | S18: 21.362273
R19: 2018-04 | S19: 5.3103854
R20: 2018-05 | S20: 8.2382575
R21: 2018-06 | S21: 1.3615486
R22: 2018-07 | S22: 4.4834308
R23: 2018-08 | S23: 10.392064

Sheet Raw_Data_Sample
A1: Order_ID | B1: Purchase_Date | C1: Approved_Date | D1: Carrier_Date | E1: Delivered_Date | F1: Estimated_Date | G1: State | H1: City | I1: Product_Category | J1: Items | K1: Product_Value | L1: Freight_Value | M1: Review_Score | N1: Delivery_Days | O1: Delay_Days | P1: Delay_Status | Q1: Approval_Hours | R1: Warehouse_Handling_Days | S1: Last_Mile_Days | T1: SLA_Bucket | U1: Exception_Flag | V1: Source_URL
A2: 35d3a51724a47ef1d0b89911e39cc4ff | B2: 42647.6 | C2: 42648.114 | D2: 42657.114 | E2: 42669.628 | F2: 42724 | G2: RS | H2: Santa Cruz Do Sul | I2: Furniture Decor | J2: 1 | K2: 39.99 | L2: 22.34 | M2: 5 | N2: =IFERROR(E2-B2,"") -> 22.027801 | O2: =IFERROR(MAX(0,E2-F2),"") -> 0 | P2: =IF(O2>0,"Delayed","On Time") -> On Time | Q2: =IFERROR((C2-B2)*24,"") -> 12.344167 | R2: =IFERROR(D2-C2,"") -> 9.0000116 | S2: =IFERROR(E2-D2,"") -> 12.513449 | T2: =IF(O2=0,"On Time/Early",IF(O2<=3,"1-3 Days Late",IF(O2<=7,"4-7 Days Late","8+ Days Late"))) -> On Time/Early | U2: =IF(P2="Delayed","Needs Review","Normal") -> Normal | V2: https://www.kaggle.com/datasets/olistbr/brazilian-ecommerce
A3: 985db56d4cabd2577d0960194dd2cd5a | B3: 42647.65 | C3: 42649.665 | D3: 42664.69 | E3: 42671.628 | F3: 42704 | G3: MG | H3: Belo Horizonte | I3: Health Beauty | J3: 1 | K3: 136.9 | L3: 17.39 | M3: 5 | N3: =IFERROR(E3-B3,"") -> 23.977928 | O3: =IFERROR(MAX(0,E3-F3),"") -> 0 | P3: =IF(O3>0,"Delayed","On Time") -> On Time | Q3: =IFERROR((C3-B3)*24,"") -> 48.360556 | R3: =IFERROR(D3-C3,"") -> 15.025475 | S3: =IFERROR(E3-D3,"") -> 6.9374306 | T3: =IF(O3=0,"On Time/Early",IF(O3<=3,"1-3 Days Late",IF(O3<=7,"4-7 Days Late","8+ Days Late"))) -> On Time/Early | U3: =IF(P3="Delayed","Needs Review","Normal") -> Normal | V3: https://www.kaggle.com/datasets/olistbr/brazilian-ecommerce
A4: a9fc3ae13c740ad46532fd50b61c69d5 | B4: 42647.947 | C4: 42649.656 | D4: 42653.656 | E4: 42656.656 | F4: 42702 | G4: MG | H4: Caetanopolis | I4: Furniture Decor | J4: 1 | K4: 19.9 | L4: 14.52 | M4: 5 | N4: =IFERROR(E4-B4,"") -> 8.7093056 | O4: =IFERROR(MAX(0,E4-F4),"") -> 0 | P4: =IF(O4>0,"Delayed","On Time") -> On Time | Q4: =IFERROR((C4-B4)*24,"") -> 41.023056 | R4: =IFERROR(D4-C4,"") -> 4.0000116 | S4: =IFERROR(E4-D4,"") -> 3 | T4: =IF(O4=0,"On Time/Early",IF(O4<=3,"1-3 Days Late",IF(O4<=7,"4-7 Days Late","8+ Days Late"))) -> On Time/Early | U4: =IF(P4="Delayed","Needs Review","Normal") -> Normal | V4: https://www.kaggle.com/datasets/olistbr/brazilian-ecommerce
A5: f31853a4f30d4851c847e4494663e749 | B5: 42649.515 | C5: 42649.599 | D5: 42658.536 | E5: 42667.872 | F5: 42704 | G5: SP | H5: Praia Grande | I5: Baby | J5: 1 | K5: 159.9 | L5: 16.33 | M5: 2 | N5: =IFERROR(E5-B5,"") -> 18.356829 | O5: =IFERROR(MAX(0,E5-F5),"") -> 0 | P5: =IF(O5>0,"Delayed","On Time") -> On Time | Q5: =IFERROR((C5-B5)*24,"") -> 2.0022222 | R5: =IFERROR(D5-C5,"") -> 8.9378009 | S5: =IFERROR(E5-D5,"") -> 9.3356019 | T5: =IF(O5=0,"On Time/Early",IF(O5<=3,"1-3 Days Late",IF(O5<=7,"4-7 Days Late","8+ Days Late"))) -> On Time/Early | U5: =IF(P5="Delayed","Needs Review","Normal") -> Normal | V5: https://www.kaggle.com/datasets/olistbr/brazilian-ecommerce
A6: 3d58fd1ee438a43f2a826dda6b013519 | B6: 42649.815 | C6: 42650.426 | D6: 42664.682 | E6: 42667.682 | F6: 42710 | G6: GO | H6: Goiania | I6: Toys | J6: 1 | K6: 41.99 | L6: 19.07 | M6: 5 | N6: =IFERROR(E6-B6,"") -> 17.866933 | O6: =IFERROR(MAX(0,E6-F6),"") -> 0 | P6: =IF(O6>0,"Delayed","On Time") -> On Time | Q6: =IFERROR((C6-B6)*24,"") -> 14.661667 | R6: =IFERROR(D6-C6,"") -> 14.25603 | S6: =IFERROR(E6-D6,"") -> 3 | T6: =IF(O6=0,"On Time/Early",IF(O6<=3,"1-3 Days Late",IF(O6<=7,"4-7 Days Late","8+ Days Late"))) -> On Time/Early | U6: =IF(P6="Delayed","Needs Review","Normal") -> Normal | V6: https://www.kaggle.com/datasets/olistbr/brazilian-ecommerce
A7: e6db6e9529fecbe14cd05dd349816656 | B7: 42741.894 | C7: 42741.9 | D7: 42744.506 | E7: 42748.582 | F7: 42786 | G7: MG | H7: Lagoa Santa | I7: Consoles Games | J7: 1 | K7: 109.9 | L7: 14.94 | M7: 4 | N7: =IFERROR(E7-B7,"") -> 6.6872685 | O7: =IFERROR(MAX(0,E7-F7),"") -> 0 | P7: =IF(O7>0,"Delayed","On Time") -> On Time | Q7: =IFERROR((C7-B7)*24,"") -> 0.12527778 | R7: =IFERROR(D7-C7,"") -> 2.606412 | S7: =IFERROR(E7-D7,"") -> 4.0756366 | T7: =IF(O7=0,"On Time/Early",IF(O7<=3,"1-3 Days Late",IF(O7<=7,"4-7 Days Late","8+ Days Late"))) -> On Time/Early | U7: =IF(P7="Delayed","Needs Review","Normal") -> Normal | V7: https://www.kaggle.com/datasets/olistbr/brazilian-ecommerce
A8: 22266e2f8d8084cd2b5d8488164d043a | B8: 42750.001 | C8: 42750.011 | D8: 42751.279 | E8: 42758.576 | F8: 42790 | G8: MG | H8: Itajuba | I8: Telephony | J8: 2 | K8: 20.98 | L8: 29.04 | M8: 4 | N8: =IFERROR(E8-B8,"") -> 8.574537 | O8: =IFERROR(MAX(0,E8-F8),"") -> 0 | P8: =IF(O8>0,"Delayed","On Time") -> On Time | Q8: =IFERROR((C8-B8)*24,"") -> 0.23222222 | R8: =IFERROR(D8-C8,"") -> 1.2684954 | S8: =IFERROR(E8-D8,"") -> 7.2963657 | T8: =IF(O8=0,"On Time/Early",IF(O8<=3,"1-3 Days Late",IF(O8<=7,"4-7 Days Late","8+ Days Late"))) -> On Time/Early | U8: =IF(P8="Delayed","Needs Review","Normal") -> Normal | V8: https://www.kaggle.com/datasets/olistbr/brazilian-ecommerce
A9: 3a6cac3e6717e6a7ee4cb28aaa149a91 | B9: 42753.843 | C9: 42753.851 | D9: 42755.464 | E9: 42762.718 | F9: 42786 | G9: MG | H9: Belo Horizonte | I9: Computers Accessories | J9: 1 | K9: 199.9 | L9: 19.99 | M9: 5 | N9: =IFERROR(E9-B9,"") -> 8.8750231 | O9: =IFERROR(MAX(0,E9-F9),"") -> 0 | P9: =IF(O9>0,"Delayed","On Time") -> On Time | Q9: =IFERROR((C9-B9)*24,"") -> 0.18194444 | R9: =IFERROR(D9-C9,"") -> 1.6129282 | S9: =IFERROR(E9-D9,"") -> 7.2545139 | T9: =IF(O9=0,"On Time/Early",IF(O9<=3,"1-3 Days Late",IF(O9<=7,"4-7 Days Late","8+ Days Late"))) -> On Time/Early | U9: =IF(P9="Delayed","Needs Review","Normal") -> Normal | V9: https://www.kaggle.com/datasets/olistbr/brazilian-ecommerce
A10: b49998737b7359ebe1b64b0b7ffb20f6 | B10: 42755.686 | C10: 42755.696 | D10: 42758.463 | E10: 42761.683 | F10: 42795 | G10: MG | H10: Monte Carmelo | I10: Cool Stuff | J10: 1 | K10: 22.3 | L10: 14.52 | M10: 4 | N10: =IFERROR(E10-B10,"") -> 5.9976505 | O10: =IFERROR(MAX(0,E10-F10),"") -> 0 | P10: =IF(O10>0,"Delayed","On Time") -> On Time | Q10: =IFERROR((C10-B10)*24,"") -> 0.24166667 | R10: =IFERROR(D10-C10,"") -> 2.7670833 | S10: =IFERROR(E10-D10,"") -> 3.2204977 | T10: =IF(O10=0,"On Time/Early",IF(O10<=3,"1-3 Days Late",IF(O10<=7,"4-7 Days Late","8+ Days Late"))) -> On Time/Early | U10: =IF(P10="Delayed","Needs Review","Normal") -> Normal | V10: https://www.kaggle.com/datasets/olistbr/brazilian-ecommerce
A11: 9786c52ca3e1ed1ef3ba5c65941627f0 | B11: 42756.883 | C11: 42757.897 | D11: 42761.465 | E11: 42775.607 | F11: 42815 | G11: PE | H11: Camaragibe | I11: Furniture Decor | J11: 1 | K11: 119.9 | L11: 50 | M11: 5 | N11: =IFERROR(E11-B11,"") -> 18.7239 | O11: =IFERROR(MAX(0,E11-F11),"") -> 0 | P11: =IF(O11>0,"Delayed","On Time") -> On Time | Q11: =IFERROR((C11-B11)*24,"") -> 24.321944 | R11: =IFERROR(D11-C11,"") -> 3.5682292 | S11: =IFERROR(E11-D11,"") -> 14.142257 | T11: =IF(O11=0,"On Time/Early",IF(O11<=3,"1-3 Days Late",IF(O11<=7,"4-7 Days Late","8+ Days Late"))) -> On Time/Early | U11: =IF(P11="Delayed","Needs Review","Normal") -> Normal | V11: https://www.kaggle.com/datasets/olistbr/brazilian-ecommerce
A12: b9581bf1b646f4fc021b131e1ca4d034 | B12: 42760.949 | C12: 42760.96 | D12: 42761.57 | E12: 42774.393 | F12: 42788 | G12: MG | H12: Itabira | I12: Garden Tools | J12: 1 | K12: 61.9 | L12: 15.64 | M12: 2 | N12: =IFERROR(E12-B12,"") -> 13.444178 | O12: =IFERROR(MAX(0,E12-F12),"") -> 0 | P12: =IF(O12>0,"Delayed","On Time") -> On Time | Q12: =IFERROR((C12-B12)*24,"") -> 0.26361111 | R12: =IFERROR(D12-C12,"") -> 0.61050926 | S12: =IFERROR(E12-D12,"") -> 12.822685 | T12: =IF(O12=0,"On Time/Early",IF(O12<=3,"1-3 Days Late",IF(O12<=7,"4-7 Days Late","8+ Days Late"))) -> On Time/Early | U12: =IF(P12="Delayed","Needs Review","Normal") -> Normal | V12: https://www.kaggle.com/datasets/olistbr/brazilian-ecommerce
A13: aa04ef5214580b06b10e2a378300db44 | B13: 42762.021 | C13: 42762.045 | D13: 42765.486 | E13: 42773.552 | F13: 42811 | G13: MG | H13: Divinopolis | I13: Health Beauty | J13: 1 | K13: 370 | L13: 19.43 | M13: 5 | N13: =IFERROR(E13-B13,"") -> 11.531505 | O13: =IFERROR(MAX(0,E13-F13),"") -> 0 | P13: =IF(O13>0,"Delayed","On Time") -> On Time | Q13: =IFERROR((C13-B13)*24,"") -> 0.58944444 | R13: =IFERROR(D13-C13,"") -> 3.4408681 | S13: =IFERROR(E13-D13,"") -> 8.0660764 | T13: =IF(O13=0,"On Time/Early",IF(O13<=3,"1-3 Days Late",IF(O13<=7,"4-7 Days Late","8+ Days Late"))) -> On Time/Early | U13: =IF(P13="Delayed","Needs Review","Normal") -> Normal | V13: https://www.kaggle.com/datasets/olistbr/brazilian-ecommerce
... A171: 9c9e682bee9157ebdd3875801b35e626 | B171: 42866.616 | C171: 42866.622 | D171: 42867.445 | E171: 42870.287 | F171: 42874 | G171: SP | H171: Sao Paulo | I171: Fixed Telephony | J171: 1 | K171: 39.99 | L171: 7.78 | M171: 5 | N171: =IFERROR(E171-B171,"") -> 3.6710417 | O171: =IFERROR(MAX(0,E171-F171),"") -> 0 | P171: =IF(O171>0,"Delayed","On Time") -> On Time | Q171: =IFERROR((C171-B171)*24,"") -> 0.13055556 | R171: =IFERROR(D171-C171,"") -> 0.82359954 | S171: =IFERROR(E171-D171,"") -> 2.8420023 | T171: =IF(O171=0,"On Time/Early",IF(O171<=3,"1-3 Days Late",IF(O171<=7,"4-7 Days Late","8+ Days Late"))) -> On Time/Early | U171: =IF(P171="Delayed","Needs Review","Normal") -> Normal | V171: https://www.kaggle.com/datasets/olistbr/brazilian-ecommerce
A172: 8a5631237c1d8626971f2867b25c076e | B172: 42866.62 | C172: 42867.627 | D172: 42870.582 | E172: 42878.492 | F172: 42886 | G172: ES | H172: Cariacica | I172: Tablets Printing Image | J172: 1 | K172: 889.99 | L172: 22.8 | N172: =IFERROR(E172-B172,"") -> 11.872049 | O172: =IFERROR(MAX(0,E172-F172),"") -> 0 | P172: =IF(O172>0,"Delayed","On Time") -> On Time | Q172: =IFERROR((C172-B172)*24,"") -> 24.175 | R172: =IFERROR(D172-C172,"") -> 2.9553356 | S172: =IFERROR(E172-D172,"") -> 7.9094213 | T172: =IF(O172=0,"On Time/Early",IF(O172<=3,"1-3 Days Late",IF(O172<=7,"4-7 Days Late","8+ Days Late"))) -> On Time/Early | U172: =IF(P172="Delayed","Needs Review","Normal") -> Normal | V172: https://www.kaggle.com/datasets/olistbr/brazilian-ecommerce
A173: 24014414a15d7274cad8a2917fe1f040 | B173: 42866.73 | C173: 42867.566 | D173: 42870.365 | E173: 42878.462 | F173: 42886 | G173: RJ | H173: Rio De Janeiro | I173: Health Beauty | J173: 2 | K173: 1308 | L173: 40.67 | M173: 5 | N173: =IFERROR(E173-B173,"") -> 11.732083 | O173: =IFERROR(MAX(0,E173-F173),"") -> 0 | P173: =IF(O173>0,"Delayed","On Time") -> On Time | Q173: =IFERROR((C173-B173)*24,"") -> 20.078056 | R173: =IFERROR(D173-C173,"") -> 2.7990856 | S173: =IFERROR(E173-D173,"") -> 8.096412 | T173: =IF(O173=0,"On Time/Early",IF(O173<=3,"1-3 Days Late",IF(O173<=7,"4-7 Days Late","8+ Days Late"))) -> On Time/Early | U173: =IF(P173="Delayed","Needs Review","Normal") -> Normal | V173: https://www.kaggle.com/datasets/olistbr/brazilian-ecommerce
A174: 26526add9da95bea7b977eff1d40d11b | B174: 42866.968 | C174: 42866.974 | D174: 42867.622 | E174: 42879.617 | F174: 42886 | G174: MG | H174: Januaria | I174: Telephony | J174: 1 | K174: 18.99 | L174: 15.1 | M174: 5 | N174: =IFERROR(E174-B174,"") -> 12.649641 | O174: =IFERROR(MAX(0,E174-F174),"") -> 0 | P174: =IF(O174>0,"Delayed","On Time") -> On Time | Q174: =IFERROR((C174-B174)*24,"") -> 0.15 | R174: =IFERROR(D174-C174,"") -> 0.6480787 | S174: =IFERROR(E174-D174,"") -> 11.995312 | T174: =IF(O174=0,"On Time/Early",IF(O174<=3,"1-3 Days Late",IF(O174<=7,"4-7 Days Late","8+ Days Late"))) -> On Time/Early | U174: =IF(P174="Delayed","Needs Review","Normal") -> Normal | V174: https://www.kaggle.com/datasets/olistbr/brazilian-ecommerce
A175: 8e337e3b4df76fa95a5e03ba9675cb56 | B175: 42867.935 | C175: 42867.941 | D175: 42871.668 | E175: 42877.37 | F175: 42886 | G175: SP | H175: Sao Paulo | I175: Bed Bath Table | J175: 2 | K175: 179.8 | L175: 24.26 | M175: 2 | N175: =IFERROR(E175-B175,"") -> 9.4343171 | O175: =IFERROR(MAX(0,E175-F175),"") -> 0 | P175: =IF(O175>0,"Delayed","On Time") -> On Time | Q175: =IFERROR((C175-B175)*24,"") -> 0.13888889 | R175: =IFERROR(D175-C175,"") -> 3.7271412 | S175: =IFERROR(E175-D175,"") -> 5.7013889 | T175: =IF(O175=0,"On Time/Early",IF(O175<=3,"1-3 Days Late",IF(O175<=7,"4-7 Days Late","8+ Days Late"))) -> On Time/Early | U175: =IF(P175="Delayed","Needs Review","Normal") -> Normal | V175: https://www.kaggle.com/datasets/olistbr/brazilian-ecommerce
A176: 193714aa21ead814cca06d425c299360 | B176: 42868.697 | C176: 42868.705 | D176: 42873.604 | E176: 42881.544 | F176: 42881 | G176: SP | H176: Jundiai | I176: Sports Leisure | J176: 1 | K176: 140 | L176: 13.54 | M176: 3 | N176: =IFERROR(E176-B176,"") -> 12.846887 | O176: =IFERROR(MAX(0,E176-F176),"") -> 0.54393519 | P176: =IF(O176>0,"Delayed","On Time") -> Delayed | Q176: =IFERROR((C176-B176)*24,"") -> 0.19194444 | R176: =IFERROR(D176-C176,"") -> 4.8986458 | S176: =IFERROR(E176-D176,"") -> 7.9402431 | T176: =IF(O176=0,"On Time/Early",IF(O176<=3,"1-3 Days Late",IF(O176<=7,"4-7 Days Late","8+ Days Late"))) -> 1-3 Days Late | U176: =IF(P176="Delayed","Needs Review","Normal") -> Needs Review | V176: https://www.kaggle.com/datasets/olistbr/brazilian-ecommerce
A177: 651bd7286b2e17e1e3ea7b644870e429 | B177: 42868.738 | C177: 42869.275 | D177: 42872.397 | E177: 42878.021 | F177: 42893 | G177: SP | H177: Ribeirao Preto | I177: Toys | J177: 1 | K177: 239 | L177: 14.01 | M177: 1 | N177: =IFERROR(E177-B177,"") -> 9.2829398 | O177: =IFERROR(MAX(0,E177-F177),"") -> 0 | P177: =IF(O177>0,"Delayed","On Time") -> On Time | Q177: =IFERROR((C177-B177)*24,"") -> 12.878056 | R177: =IFERROR(D177-C177,"") -> 3.1228588 | S177: =IFERROR(E177-D177,"") -> 5.6234954 | T177: =IF(O177=0,"On Time/Early",IF(O177<=3,"1-3 Days Late",IF(O177<=7,"4-7 Days Late","8+ Days Late"))) -> On Time/Early | U177: =IF(P177="Delayed","Needs Review","Normal") -> Normal | V177: https://www.kaggle.com/datasets/olistbr/brazilian-ecommerce
A178: 0168a7f186c1f066748d15d8c51f489a | B178: 42868.76 | C178: 42871.143 | D178: 42872.494 | E178: 42873.429 | F178: 42879 | G178: SP | H178: Suzano | I178: Housewares | J178: 1 | K178: 149.9 | L178: 8.3 | M178: 4 | N178: =IFERROR(E178-B178,"") -> 4.6689583 | O178: =IFERROR(MAX(0,E178-F178),"") -> 0 | P178: =IF(O178>0,"Delayed","On Time") -> On Time | Q178: =IFERROR((C178-B178)*24,"") -> 57.175556 | R178: =IFERROR(D178-C178,"") -> 1.3511574 | S178: =IFERROR(E178-D178,"") -> 0.93548611 | T178: =IF(O178=0,"On Time/Early",IF(O178<=3,"1-3 Days Late",IF(O178<=7,"4-7 Days Late","8+ Days Late"))) -> On Time/Early | U178: =IF(P178="Delayed","Needs Review","Normal") -> Normal | V178: https://www.kaggle.com/datasets/olistbr/brazilian-ecommerce
A179: 001d8f0e34a38c37f7dba2a37d4eba8b | B179: 42869.722 | C179: 42869.733 | D179: 42879.656 | E179: 42881.552 | F179: 42879 | G179: SP | H179: Sao Paulo | I179: Health Beauty | J179: 2 | K179: 37.98 | L179: 15.56 | M179: 1 | N179: =IFERROR(E179-B179,"") -> 11.829931 | O179: =IFERROR(MAX(0,E179-F179),"") -> 2.5519676 | P179: =IF(O179>0,"Delayed","On Time") -> Delayed | Q179: =IFERROR((C179-B179)*24,"") -> 0.2575 | R179: =IFERROR(D179-C179,"") -> 9.9234954 | S179: =IFERROR(E179-D179,"") -> 1.895706 | T179: =IF(O179=0,"On Time/Early",IF(O179<=3,"1-3 Days Late",IF(O179<=7,"4-7 Days Late","8+ Days Late"))) -> 1-3 Days Late | U179: =IF(P179="Delayed","Needs Review","Normal") -> Needs Review | V179: https://www.kaggle.com/datasets/olistbr/brazilian-ecommerce
A180: fd2b4179de3cceb73bc884f6c19d85d0 | B180: 42869.773 | C180: 42869.781 | D180: 42874.471 | E180: 42885.527 | F180: 42899 | G180: DF | H180: Brasilia | I180: Auto | J180: 1 | K180: 31.99 | L180: 34.15 | M180: 5 | N180: =IFERROR(E180-B180,"") -> 15.753137 | O180: =IFERROR(MAX(0,E180-F180),"") -> 0 | P180: =IF(O180>0,"Delayed","On Time") -> On Time | Q180: =IFERROR((C180-B180)*24,"") -> 0.19055556 | R180: =IFERROR(D180-C180,"") -> 4.689375 | S180: =IFERROR(E180-D180,"") -> 11.055822 | T180: =IF(O180=0,"On Time/Early",IF(O180<=3,"1-3 Days Late",IF(O180<=7,"4-7 Days Late","8+ Days Late"))) -> On Time/Early | U180: =IF(P180="Delayed","Needs Review","Normal") -> Normal | V180: https://www.kaggle.com/datasets/olistbr/brazilian-ecommerce
A181: d7520dd6301787392e59dddbbc68ea22 | B181: 42869.804 | C181: 42870.809 | D181: 42873.551 | E181: 42877.379 | F181: 42879 | G181: SP | H181: Sao Paulo | I181: Cool Stuff | J181: 1 | K181: 39.9 | L181: 8.72 | M181: 5 | N181: =IFERROR(E181-B181,"") -> 7.574213 | O181: =IFERROR(MAX(0,E181-F181),"") -> 0 | P181: =IF(O181>0,"Delayed","On Time") -> On Time | Q181: =IFERROR((C181-B181)*24,"") -> 24.118611 | R181: =IFERROR(D181-C181,"") -> 2.7414236 | S181: =IFERROR(E181-D181,"") -> 3.8278472 | T181: =IF(O181=0,"On Time/Early",IF(O181<=3,"1-3 Days Late",IF(O181<=7,"4-7 Days Late","8+ Days Late"))) -> On Time/Early | U181: =IF(P181="Delayed","Needs Review","Normal") -> Normal | V181: https://www.kaggle.com/datasets/olistbr/brazilian-ecommerce
A182: 6607ca536882b974ea594bc640b01519 | B182: 42869.875 | C182: 42869.882 | D182: 42872.287 | E182: 42877.554 | F182: 42886 | G182: SP | H182: Sao Paulo | I182: Bed Bath Table | J182: 1 | K182: 139.9 | L182: 14 | N182: =IFERROR(E182-B182,"") -> 7.6786458 | O182: =IFERROR(MAX(0,E182-F182),"") -> 0 | P182: =IF(O182>0,"Delayed","On Time") -> On Time | Q182: =IFERROR((C182-B182)*24,"") -> 0.16055556 | R182: =IFERROR(D182-C182,"") -> 2.404375 | S182: =IFERROR(E182-D182,"") -> 5.267581 | T182: =IF(O182=0,"On Time/Early",IF(O182<=3,"1-3 Days Late",IF(O182<=7,"4-7 Days Late","8+ Days Late"))) -> On Time/Early | U182: =IF(P182="Delayed","Needs Review","Normal") -> Normal | V182: https://www.kaggle.com/datasets/olistbr/brazilian-ecommerce
A183: 22f469f96aaa1fdd00d0ac66369a950f | B183: 42869.914 | C183: 42869.924 | D183: 42872.443 | E183: 42879.644 | F183: 42888 | G183: SP | H183: Ubatuba | I183: Watches Gifts | J183: 1 | K183: 52.5 | L183: 15.12 | M183: 4 | N183: =IFERROR(E183-B183,"") -> 9.7304514 | O183: =IFERROR(MAX(0,E183-F183),"") -> 0 | P183: =IF(O183>0,"Delayed","On Time") -> On Time | Q183: =IFERROR((C183-B183)*24,"") -> 0.23416667 | R183: =IFERROR(D183-C183,"") -> 2.5190046 | S183: =IFERROR(E183-D183,"") -> 7.2016898 | T183: =IF(O183=0,"On Time/Early",IF(O183<=3,"1-3 Days Late",IF(O183<=7,"4-7 Days Late","8+ Days Late"))) -> On Time/Early | U183: =IF(P183="Delayed","Needs Review","Normal") -> Normal | V183: https://www.kaggle.com/datasets/olistbr/brazilian-ecommerce
A184: ca91862f94f3eb805b394ae462b669a6 | B184: 42870.041 | C184: 42870.049 | D184: 42872.607 | E184: 42873.523 | F184: 42879 | G184: SP | H184: Sao Paulo | I184: Telephony | J184: 2 | K184: 59.98 | L184: 15.56 | M184: 5 | N184: =IFERROR(E184-B184,"") -> 3.4818866 | O184: =IFERROR(MAX(0,E184-F184),"") -> 0 | P184: =IF(O184>0,"Delayed","On Time") -> On Time | Q184: =IFERROR((C184-B184)*24,"") -> 0.17472222 | R184: =IFERROR(D184-C184,"") -> 2.5578588 | S184: =IFERROR(E184-D184,"") -> 0.91674769 | T184: =IF(O184=0,"On Time/Early",IF(O184<=3,"1-3 Days Late",IF(O184<=7,"4-7 Days Late","8+ Days Late"))) -> On Time/Early | U184: =IF(P184="Delayed","Needs Review","Normal") -> Normal | V184: https://www.kaggle.com/datasets/olistbr/brazilian-ecommerce
A185: 71ea8340051d1eb026b7f104899eafe9 | B185: 42870.566 | C185: 42872.174 | D185: 42872.685 | E185: 42877.536 | F185: 42895 | G185: SP | H185: Sao Paulo | I185: Computers Accessories | J185: 1 | K185: 207.3 | L185: 16.2 | M185: 5 | N185: =IFERROR(E185-B185,"") -> 6.970544 | O185: =IFERROR(MAX(0,E185-F185),"") -> 0 | P185: =IF(O185>0,"Delayed","On Time") -> On Time | Q185: =IFERROR((C185-B185)*24,"") -> 38.598889 | R185: =IFERROR(D185-C185,"") -> 0.51075231 | S185: =IFERROR(E185-D185,"") -> 4.8515046 | T185: =IF(O185=0,"On Time/Early",IF(O185<=3,"1-3 Days Late",IF(O185<=7,"4-7 Days Late","8+ Days Late"))) -> On Time/Early | U185: =IF(P185="Delayed","Needs Review","Normal") -> Normal | V185: https://www.kaggle.com/datasets/olistbr/brazilian-ecommerce
A186: c3cb4c7c4b963ab08b07a5dca5baf05d | B186: 42870.687 | C186: 42871.149 | D186: 42872.392 | E186: 42878.536 | F186: 42894 | G186: RS | H186: Trindade Do Sul | I186: Stationery | J186: 1 | K186: 119 | L186: 15.58 | M186: 5 | N186: =IFERROR(E186-B186,"") -> 7.849213 | O186: =IFERROR(MAX(0,E186-F186),"") -> 0 | P186: =IF(O186>0,"Delayed","On Time") -> On Time | Q186: =IFERROR((C186-B186)*24,"") -> 11.103611 | R186: =IFERROR(D186-C186,"") -> 1.2427662 | S186: =IFERROR(E186-D186,"") -> 6.1437963 | T186: =IF(O186=0,"On Time/Early",IF(O186<=3,"1-3 Days Late",IF(O186<=7,"4-7 Days Late","8+ Days Late"))) -> On Time/Early | U186: =IF(P186="Delayed","Needs Review","Normal") -> Normal | V186: https://www.kaggle.com/datasets/olistbr/brazilian-ecommerce
A187: 123a6b2b8763ca40782c8252e63fdbca | B187: 42870.718 | C187: 42872.168 | D187: 42877.66 | E187: 42885.644 | F187: 42892 | G187: PR | H187: Campo Mourao | I187: Computers Accessories | J187: 1 | K187: 177 | L187: 17 | M187: 4 | N187: =IFERROR(E187-B187,"") -> 14.926701 | O187: =IFERROR(MAX(0,E187-F187),"") -> 0 | P187: =IF(O187>0,"Delayed","On Time") -> On Time | Q187: =IFERROR((C187-B187)*24,"") -> 34.819722 | R187: =IFERROR(D187-C187,"") -> 5.4911458 | S187: =IFERROR(E187-D187,"") -> 7.9847338 | T187: =IF(O187=0,"On Time/Early",IF(O187<=3,"1-3 Days Late",IF(O187<=7,"4-7 Days Late","8+ Days Late"))) -> On Time/Early | U187: =IF(P187="Delayed","Needs Review","Normal") -> Normal | V187: https://www.kaggle.com/datasets/olistbr/brazilian-ecommerce
A188: c15582dfe92312e48613b9cb37caf0c8 | B188: 42870.76 | C188: 42872.17 | D188: 42873.447 | E188: 42881.332 | F188: 42900 | G188: GO | H188: Carmo Do Rio Verde | I188: Health Beauty | J188: 1 | K188: 89.99 | L188: 15.38 | M188: 5 | N188: =IFERROR(E188-B188,"") -> 10.572685 | O188: =IFERROR(MAX(0,E188-F188),"") -> 0 | P188: =IF(O188>0,"Delayed","On Time") -> On Time | Q188: =IFERROR((C188-B188)*24,"") -> 33.856111 | R188: =IFERROR(D188-C188,"") -> 1.2765278 | S188: =IFERROR(E188-D188,"") -> 7.8854861 | T188: =IF(O188=0,"On Time/Early",IF(O188<=3,"1-3 Days Late",IF(O188<=7,"4-7 Days Late","8+ Days Late"))) -> On Time/Early | U188: =IF(P188="Delayed","Needs Review","Normal") -> Normal | V188: https://www.kaggle.com/datasets/olistbr/brazilian-ecommerce
A189: 04eb8bac62618bbc56c582cd49493669 | B189: 42871.384 | C189: 42871.393 | D189: 42872.633 | E189: 42878.356 | F189: 42900 | G189: RJ | H189: Sao Goncalo | I189: Fashion Bags Accessories | J189: 1 | K189: 69.9 | L189: 14.24 | M189: 4 | N189: =IFERROR(E189-B189,"") -> 6.9723843 | O189: =IFERROR(MAX(0,E189-F189),"") -> 0 | P189: =IF(O189>0,"Delayed","On Time") -> On Time | Q189: =IFERROR((C189-B189)*24,"") -> 0.21083333 | R189: =IFERROR(D189-C189,"") -> 1.2400116 | S189: =IFERROR(E189-D189,"") -> 5.723588 | T189: =IF(O189=0,"On Time/Early",IF(O189<=3,"1-3 Days Late",IF(O189<=7,"4-7 Days Late","8+ Days Late"))) -> On Time/Early | U189: =IF(P189="Delayed","Needs Review","Normal") -> Normal | V189: https://www.kaggle.com/datasets/olistbr/brazilian-ecommerce
A190: 7195bbe2eb284effff29db46278daad8 | B190: 42871.41 | C190: 42872.413 | D190: 42873.641 | E190: 42880.379 | F190: 42899 | G190: RJ | H190: Mesquita | I190: Baby | J190: 1 | K190: 50 | L190: 16.6 | M190: 5 | N190: =IFERROR(E190-B190,"") -> 8.9687731 | O190: =IFERROR(MAX(0,E190-F190),"") -> 0 | P190: =IF(O190>0,"Delayed","On Time") -> On Time | Q190: =IFERROR((C190-B190)*24,"") -> 24.079722 | R190: =IFERROR(D190-C190,"") -> 1.2273495 | S190: =IFERROR(E190-D190,"") -> 6.7381019 | T190: =IF(O190=0,"On Time/Early",IF(O190<=3,"1-3 Days Late",IF(O190<=7,"4-7 Days Late","8+ Days Late"))) -> On Time/Early | U190: =IF(P190="Delayed","Needs Review","Normal") -> Normal | V190: https://www.kaggle.com/datasets/olistbr/brazilian-ecommerce
A191: b9fa782d4918580e25b6e3b516a55710 | B191: 42871.451 | C191: 42871.462 | D191: 42872.625 | E191: 42878.529 | F191: 42892 | G191: SP | H191: Sao Paulo | I191: Bed Bath Table | J191: 1 | K191: 89.9 | L191: 12.13 | M191: 5 | N191: =IFERROR(E191-B191,"") -> 7.0783449 | O191: =IFERROR(MAX(0,E191-F191),"") -> 0 | P191: =IF(O191>0,"Delayed","On Time") -> On Time | Q191: =IFERROR((C191-B191)*24,"") -> 0.26194444 | R191: =IFERROR(D191-C191,"") -> 1.1632523 | S191: =IFERROR(E191-D191,"") -> 5.9041782 | T191: =IF(O191=0,"On Time/Early",IF(O191<=3,"1-3 Days Late",IF(O191<=7,"4-7 Days Late","8+ Days Late"))) -> On Time/Early | U191: =IF(P191="Delayed","Needs Review","Normal") -> Normal | V191: https://www.kaggle.com/datasets/olistbr/brazilian-ecommerce
A192: 45ab65433b358cdb30d0f2af36c96e7c | B192: 42871.525 | C192: 42871.549 | D192: 42872.422 | E192: 42877.572 | F192: 42893 | G192: SP | H192: Sao Paulo | I192: Computers Accessories | J192: 1 | K192: 199.9 | L192: 18.65 | M192: 5 | N192: =IFERROR(E192-B192,"") -> 6.0465046 | O192: =IFERROR(MAX(0,E192-F192),"") -> 0 | P192: =IF(O192>0,"Delayed","On Time") -> On Time | Q192: =IFERROR((C192-B192)*24,"") -> 0.57166667 | R192: =IFERROR(D192-C192,"") -> 0.87327546 | S192: =IFERROR(E192-D192,"") -> 5.1494097 | T192: =IF(O192=0,"On Time/Early",IF(O192<=3,"1-3 Days Late",IF(O192<=7,"4-7 Days Late","8+ Days Late"))) -> On Time/Early | U192: =IF(P192="Delayed","Needs Review","Normal") -> Normal | V192: https://www.kaggle.com/datasets/olistbr/brazilian-ecommerce
A193: c7d3893304861d303bb8f6193525bbf0 | B193: 42871.814 | C193: 42871.823 | D193: 42872.511 | E193: 42878.476 | F193: 42902 | G193: BA | H193: Salvador | I193: Toys | J193: 1 | K193: 145.9 | L193: 18.59 | M193: 5 | N193: =IFERROR(E193-B193,"") -> 6.6621759 | O193: =IFERROR(MAX(0,E193-F193),"") -> 0 | P193: =IF(O193>0,"Delayed","On Time") -> On Time | Q193: =IFERROR((C193-B193)*24,"") -> 0.22333333 | R193: =IFERROR(D193-C193,"") -> 0.68829861 | S193: =IFERROR(E193-D193,"") -> 5.9645718 | T193: =IF(O193=0,"On Time/Early",IF(O193<=3,"1-3 Days Late",IF(O193<=7,"4-7 Days Late","8+ Days Late"))) -> On Time/Early | U193: =IF(P193="Delayed","Needs Review","Normal") -> Normal | V193: https://www.kaggle.com/datasets/olistbr/brazilian-ecommerce
A194: 7ac13b045c748b7eef3f9011bd5683c9 | B194: 42872.735 | C194: 42872.743 | D194: 42873.361 | E194: 42874.437 | F194: 42894 | G194: SP | H194: Cotia | I194: Computers Accessories | J194: 1 | K194: 39.9 | L194: 14.1 | M194: 5 | N194: =IFERROR(E194-B194,"") -> 1.7020486 | O194: =IFERROR(MAX(0,E194-F194),"") -> 0 | P194: =IF(O194>0,"Delayed","On Time") -> On Time | Q194: =IFERROR((C194-B194)*24,"") -> 0.19166667 | R194: =IFERROR(D194-C194,"") -> 0.61789352 | S194: =IFERROR(E194-D194,"") -> 1.076169 | T194: =IF(O194=0,"On Time/Early",IF(O194<=3,"1-3 Days Late",IF(O194<=7,"4-7 Days Late","8+ Days Late"))) -> On Time/Early | U194: =IF(P194="Delayed","Needs Review","Normal") -> Normal | V194: https://www.kaggle.com/datasets/olistbr/brazilian-ecommerce
... A206: a797f338da66eefca816db5328d5e5ab | B206: 42878.631 | C206: 42878.641 | D206: 42879.548 | E206: 42887.478 | F206: 42912 | G206: RS | H206: Campo Bom | I206: Housewares | J206: 3 | K206: 143.97 | L206: 45.33 | M206: 1 | N206: =IFERROR(E206-B206,"") -> 8.8468056 | O206: =IFERROR(MAX(0,E206-F206),"") -> 0 | P206: =IF(O206>0,"Delayed","On Time") -> On Time | Q206: =IFERROR((C206-B206)*24,"") -> 0.24416667 | R206: =IFERROR(D206-C206,"") -> 0.90711806 | S206: =IFERROR(E206-D206,"") -> 7.9295139 | T206: =IF(O206=0,"On Time/Early",IF(O206<=3,"1-3 Days Late",IF(O206<=7,"4-7 Days Late","8+ Days Late"))) -> On Time/Early | U206: =IF(P206="Delayed","Needs Review","Normal") -> Normal | V206: https://www.kaggle.com/datasets/olistbr/brazilian-ecommerce
A207: 42ba338f99f42e0261e5897c7da157c5 | B207: 42878.638 | C207: 42878.649 | D207: 42879.395 | E207: 42886.371 | F207: 42898 | G207: SP | H207: Sao Paulo | I207: Sports Leisure | J207: 1 | K207: 69.9 | L207: 11.99 | N207: =IFERROR(E207-B207,"") -> 7.7321528 | O207: =IFERROR(MAX(0,E207-F207),"") -> 0 | P207: =IF(O207>0,"Delayed","On Time") -> On Time | Q207: =IFERROR((C207-B207)*24,"") -> 0.26583333 | R207: =IFERROR(D207-C207,"") -> 0.74516204 | S207: =IFERROR(E207-D207,"") -> 6.9759144 | T207: =IF(O207=0,"On Time/Early",IF(O207<=3,"1-3 Days Late",IF(O207<=7,"4-7 Days Late","8+ Days Late"))) -> On Time/Early | U207: =IF(P207="Delayed","Needs Review","Normal") -> Normal | V207: https://www.kaggle.com/datasets/olistbr/brazilian-ecommerce
A208: 6311e2bf4ff2a50d88a27f8178ed0282 | B208: 42879.399 | C208: 42879.407 | D208: 42886.453 | E208: 42893.366 | F208: 42892 | G208: SP | H208: Sao Paulo | I208: Cool Stuff | J208: 1 | K208: 129.99 | L208: 12.11 | M208: 3 | N208: =IFERROR(E208-B208,"") -> 13.966562 | O208: =IFERROR(MAX(0,E208-F208),"") -> 1.3656481 | P208: =IF(O208>0,"Delayed","On Time") -> Delayed | Q208: =IFERROR((C208-B208)*24,"") -> 0.17833333 | R208: =IFERROR(D208-C208,"") -> 7.0466782 | S208: =IFERROR(E208-D208,"") -> 6.9124537 | T208: =IF(O208=0,"On Time/Early",IF(O208<=3,"1-3 Days Late",IF(O208<=7,"4-7 Days Late","8+ Days Late"))) -> 1-3 Days Late | U208: =IF(P208="Delayed","Needs Review","Normal") -> Needs Review | V208: https://www.kaggle.com/datasets/olistbr/brazilian-ecommerce
A209: 170080bcc0fb2580b853e32c5c579d5f | B209: 42879.425 | C209: 42880.601 | D209: 42884.408 | E209: 42916.689 | F209: 42908 | G209: BA | H209: Salvador | I209: Furniture Decor | J209: 1 | K209: 38.5 | L209: 17.92 | M209: 5 | N209: =IFERROR(E209-B209,"") -> 37.26412 | O209: =IFERROR(MAX(0,E209-F209),"") -> 8.6894213 | P209: =IF(O209>0,"Delayed","On Time") -> Delayed | Q209: =IFERROR((C209-B209)*24,"") -> 28.213056 | R209: =IFERROR(D209-C209,"") -> 3.8073843 | S209: =IFERROR(E209-D209,"") -> 32.281192 | T209: =IF(O209=0,"On Time/Early",IF(O209<=3,"1-3 Days Late",IF(O209<=7,"4-7 Days Late","8+ Days Late"))) -> 8+ Days Late | U209: =IF(P209="Delayed","Needs Review","Normal") -> Needs Review | V209: https://www.kaggle.com/datasets/olistbr/brazilian-ecommerce
A210: ba32150c10a6a25c26b1695af824c419 | B210: 42879.489 | C210: 42879.503 | D210: 42879.572 | E210: 42887.662 | F210: 42899 | G210: SP | H210: Jundiai | I210: Health Beauty | J210: 1 | K210: 49.99 | L210: 12.69 | M210: 4 | N210: =IFERROR(E210-B210,"") -> 8.1737847 | O210: =IFERROR(MAX(0,E210-F210),"") -> 0 | P210: =IF(O210>0,"Delayed","On Time") -> On Time | Q210: =IFERROR((C210-B210)*24,"") -> 0.33694444 | R210: =IFERROR(D210-C210,"") -> 0.069016204 | S210: =IFERROR(E210-D210,"") -> 8.0907292 | T210: =IF(O210=0,"On Time/Early",IF(O210<=3,"1-3 Days Late",IF(O210<=7,"4-7 Days Late","8+ Days Late"))) -> On Time/Early | U210: =IF(P210="Delayed","Needs Review","Normal") -> Normal | V210: https://www.kaggle.com/datasets/olistbr/brazilian-ecommerce
A211: afde4304cb6e11145784b6ea2126bb33 | B211: 42881.318 | C211: 42881.327 | D211: 42881.477 | E211: 42886.583 | F211: 42902 | G211: SP | H211: Itapetininga | I211: Housewares | J211: 1 | K211: 92.5 | L211: 13.67 | M211: 1 | N211: =IFERROR(E211-B211,"") -> 5.2653241 | O211: =IFERROR(MAX(0,E211-F211),"") -> 0 | P211: =IF(O211>0,"Delayed","On Time") -> On Time | Q211: =IFERROR((C211-B211)*24,"") -> 0.20722222 | R211: =IFERROR(D211-C211,"") -> 0.15046296 | S211: =IFERROR(E211-D211,"") -> 5.1062269 | T211: =IF(O211=0,"On Time/Early",IF(O211<=3,"1-3 Days Late",IF(O211<=7,"4-7 Days Late","8+ Days Late"))) -> On Time/Early | U211: =IF(P211="Delayed","Needs Review","Normal") -> Normal | V211: https://www.kaggle.com/datasets/olistbr/brazilian-ecommerce
A212: 786baaa6b659351627edf0bbbee0648a | B212: 42882.003 | C212: 42882.049 | D212: 42884.632 | E212: 42888.665 | F212: 42908 | G212: PR | H212: Francisco Beltrao | I212: Health Beauty | J212: 1 | K212: 370 | L212: 15.61 | M212: 5 | N212: =IFERROR(E212-B212,"") -> 6.661875 | O212: =IFERROR(MAX(0,E212-F212),"") -> 0 | P212: =IF(O212>0,"Delayed","On Time") -> On Time | Q212: =IFERROR((C212-B212)*24,"") -> 1.0936111 | R212: =IFERROR(D212-C212,"") -> 2.5835764 | S212: =IFERROR(E212-D212,"") -> 4.0327315 | T212: =IF(O212=0,"On Time/Early",IF(O212<=3,"1-3 Days Late",IF(O212<=7,"4-7 Days Late","8+ Days Late"))) -> On Time/Early | U212: =IF(P212="Delayed","Needs Review","Normal") -> Normal | V212: https://www.kaggle.com/datasets/olistbr/brazilian-ecommerce
A213: 0a02d8b1995030c91c63add1acba1fb2 | B213: 42882.576 | C213: 42883.58 | D213: 42884.655 | E213: 42885.399 | F213: 42895 | G213: SP | H213: Sao Paulo | I213: Toys | J213: 1 | K213: 94.9 | L213: 7.92 | M213: 5 | N213: =IFERROR(E213-B213,"") -> 2.8230671 | O213: =IFERROR(MAX(0,E213-F213),"") -> 0 | P213: =IF(O213>0,"Delayed","On Time") -> On Time | Q213: =IFERROR((C213-B213)*24,"") -> 24.106944 | R213: =IFERROR(D213-C213,"") -> 1.0750694 | S213: =IFERROR(E213-D213,"") -> 0.74354167 | T213: =IF(O213=0,"On Time/Early",IF(O213<=3,"1-3 Days Late",IF(O213<=7,"4-7 Days Late","8+ Days Late"))) -> On Time/Early | U213: =IF(P213="Delayed","Needs Review","Normal") -> Normal | V213: https://www.kaggle.com/datasets/olistbr/brazilian-ecommerce
A214: d3eb3d3d09637fa9093a25b933eaf1d4 | B214: 42882.584 | C214: 42885.21 | D214: 42885.389 | E214: 42899.488 | F214: 42913 | G214: SC | H214: Jaragua Do Sul | I214: Consoles Games | J214: 1 | K214: 8.99 | L214: 16.79 | M214: 4 | N214: =IFERROR(E214-B214,"") -> 16.903322 | O214: =IFERROR(MAX(0,E214-F214),"") -> 0 | P214: =IF(O214>0,"Delayed","On Time") -> On Time | Q214: =IFERROR((C214-B214)*24,"") -> 63.021389 | R214: =IFERROR(D214-C214,"") -> 0.17866898 | S214: =IFERROR(E214-D214,"") -> 14.098762 | T214: =IF(O214=0,"On Time/Early",IF(O214<=3,"1-3 Days Late",IF(O214<=7,"4-7 Days Late","8+ Days Late"))) -> On Time/Early | U214: =IF(P214="Delayed","Needs Review","Normal") -> Normal | V214: https://www.kaggle.com/datasets/olistbr/brazilian-ecommerce
A215: e2ec4ae060b3e2662724575b47ac605c | B215: 42882.75 | C215: 42882.757 | D215: 42884.464 | E215: 42891.625 | F215: 42909 | G215: SP | H215: Sao Jose Dos Campos | I215: Sports Leisure | J215: 1 | K215: 89.9 | L215: 21.12 | M215: 4 | N215: =IFERROR(E215-B215,"") -> 8.8749653 | O215: =IFERROR(MAX(0,E215-F215),"") -> 0 | P215: =IF(O215>0,"Delayed","On Time") -> On Time | Q215: =IFERROR((C215-B215)*24,"") -> 0.17416667 | R215: =IFERROR(D215-C215,"") -> 1.7072338 | S215: =IFERROR(E215-D215,"") -> 7.1604745 | T215: =IF(O215=0,"On Time/Early",IF(O215<=3,"1-3 Days Late",IF(O215<=7,"4-7 Days Late","8+ Days Late"))) -> On Time/Early | U215: =IF(P215="Delayed","Needs Review","Normal") -> Normal | V215: https://www.kaggle.com/datasets/olistbr/brazilian-ecommerce
A216: 5857c4471757f3c88440e2f2f405c7c1 | B216: 42883.768 | C216: 42885.191 | D216: 42886.3 | E216: 42891.571 | F216: 42906 | G216: SP | H216: Santa Albertina | I216: Perfumery | J216: 1 | K216: 56.99 | L216: 11.9 | M216: 3 | N216: =IFERROR(E216-B216,"") -> 7.8027662 | O216: =IFERROR(MAX(0,E216-F216),"") -> 0 | P216: =IF(O216>0,"Delayed","On Time") -> On Time | Q216: =IFERROR((C216-B216)*24,"") -> 34.150278 | R216: =IFERROR(D216-C216,"") -> 1.1089699 | S216: =IFERROR(E216-D216,"") -> 5.2708681 | T216: =IF(O216=0,"On Time/Early",IF(O216<=3,"1-3 Days Late",IF(O216<=7,"4-7 Days Late","8+ Days Late"))) -> On Time/Early | U216: =IF(P216="Delayed","Needs Review","Normal") -> Normal | V216: https://www.kaggle.com/datasets/olistbr/brazilian-ecommerce
A217: ca7a8803c5feb9da44e133b9f9626dc3 | B217: 42884.501 | C217: 42884.511 | D217: 42884.549 | E217: 42895.346 | F217: 42908 | G217: SP | H217: Fernandopolis | I217: Watches Gifts | J217: 1 | K217: 590.82 | L217: 15.64 | M217: 5 | N217: =IFERROR(E217-B217,"") -> 10.844745 | O217: =IFERROR(MAX(0,E217-F217),"") -> 0 | P217: =IF(O217>0,"Delayed","On Time") -> On Time | Q217: =IFERROR((C217-B217)*24,"") -> 0.2325 | R217: =IFERROR(D217-C217,"") -> 0.038564815 | S217: =IFERROR(E217-D217,"") -> 10.796493 | T217: =IF(O217=0,"On Time/Early",IF(O217<=3,"1-3 Days Late",IF(O217<=7,"4-7 Days Late","8+ Days Late"))) -> On Time/Early | U217: =IF(P217="Delayed","Needs Review","Normal") -> Normal | V217: https://www.kaggle.com/datasets/olistbr/brazilian-ecommerce
A218: 43ee3ed7fa79e982fb7de9363c7832e3 | B218: 42884.721 | C218: 42884.729 | D218: 42887.384 | E218: 42892.774 | F218: 42907 | G218: MG | H218: Uberaba | I218: Health Beauty | J218: 1 | K218: 18.99 | L218: 15.1 | M218: 5 | N218: =IFERROR(E218-B218,"") -> 8.0527546 | O218: =IFERROR(MAX(0,E218-F218),"") -> 0 | P218: =IF(O218>0,"Delayed","On Time") -> On Time | Q218: =IFERROR((C218-B218)*24,"") -> 0.19361111 | R218: =IFERROR(D218-C218,"") -> 2.6551042 | S218: =IFERROR(E218-D218,"") -> 5.3895833 | T218: =IF(O218=0,"On Time/Early",IF(O218<=3,"1-3 Days Late",IF(O218<=7,"4-7 Days Late","8+ Days Late"))) -> On Time/Early | U218: =IF(P218="Delayed","Needs Review","Normal") -> Normal | V218: https://www.kaggle.com/datasets/olistbr/brazilian-ecommerce
A219: 7dc2cd8c070cb20ae535d75d107741de | B219: 42884.733 | C219: 42884.74 | D219: 42885.605 | E219: 42893.596 | F219: 42908 | G219: MG | H219: Belo Horizonte | I219: Bed Bath Table | J219: 1 | K219: 269.9 | L219: 22.38 | M219: 5 | N219: =IFERROR(E219-B219,"") -> 8.8633449 | O219: =IFERROR(MAX(0,E219-F219),"") -> 0 | P219: =IF(O219>0,"Delayed","On Time") -> On Time | Q219: =IFERROR((C219-B219)*24,"") -> 0.1675 | R219: =IFERROR(D219-C219,"") -> 0.86560185 | S219: =IFERROR(E219-D219,"") -> 7.9907639 | T219: =IF(O219=0,"On Time/Early",IF(O219<=3,"1-3 Days Late",IF(O219<=7,"4-7 Days Late","8+ Days Late"))) -> On Time/Early | U219: =IF(P219="Delayed","Needs Review","Normal") -> Normal | V219: https://www.kaggle.com/datasets/olistbr/brazilian-ecommerce
... A238: 40d2a869f24d0fcaf5a569330470313d | B238: 42891.667 | C238: 42891.733 | D238: 42892.63 | E238: 42908.668 | F238: 42905 | G238: SP | H238: Hortolandia | I238: Audio | J238: 1 | K238: 75 | L238: 7.78 | M238: 1 | N238: =IFERROR(E238-B238,"") -> 17.001123 | O238: =IFERROR(MAX(0,E238-F238),"") -> 3.6684144 | P238: =IF(O238>0,"Delayed","On Time") -> Delayed | Q238: =IFERROR((C238-B238)*24,"") -> 1.5713889 | R238: =IFERROR(D238-C238,"") -> 0.89677083 | S238: =IFERROR(E238-D238,"") -> 16.038877 | T238: =IF(O238=0,"On Time/Early",IF(O238<=3,"1-3 Days Late",IF(O238<=7,"4-7 Days Late","8+ Days Late"))) -> 4-7 Days Late | U238: =IF(P238="Delayed","Needs Review","Normal") -> Needs Review | V238: https://www.kaggle.com/datasets/olistbr/brazilian-ecommerce
A239: 0c384d67524b5b92aa2fa6c8baa9a983 | B239: 42891.806 | C239: 42891.813 | D239: 42893.474 | E239: 42899.59 | F239: 42913 | G239: SP | H239: Guarulhos | I239: Bed Bath Table | J239: 1 | K239: 89.9 | L239: 12.13 | N239: =IFERROR(E239-B239,"") -> 7.7841435 | O239: =IFERROR(MAX(0,E239-F239),"") -> 0 | P239: =IF(O239>0,"Delayed","On Time") -> On Time | Q239: =IFERROR((C239-B239)*24,"") -> 0.16861111 | R239: =IFERROR(D239-C239,"") -> 1.6616667 | S239: =IFERROR(E239-D239,"") -> 6.1154514 | T239: =IF(O239=0,"On Time/Early",IF(O239<=3,"1-3 Days Late",IF(O239<=7,"4-7 Days Late","8+ Days Late"))) -> On Time/Early | U239: =IF(P239="Delayed","Needs Review","Normal") -> Normal | V239: https://www.kaggle.com/datasets/olistbr/brazilian-ecommerce
A240: d2a63eace67f829427a227b535bf9b5c | B240: 42891.885 | C240: 42893.115 | D240: 42894.707 | E240: 42902.594 | F240: 42914 | G240: MG | H240: Resplendor | I240: Telephony | J240: 1 | K240: 18.99 | L240: 15.1 | M240: 5 | N240: =IFERROR(E240-B240,"") -> 10.709456 | O240: =IFERROR(MAX(0,E240-F240),"") -> 0 | P240: =IF(O240>0,"Delayed","On Time") -> On Time | Q240: =IFERROR((C240-B240)*24,"") -> 29.524444 | R240: =IFERROR(D240-C240,"") -> 1.5916898 | S240: =IFERROR(E240-D240,"") -> 7.887581 | T240: =IF(O240=0,"On Time/Early",IF(O240<=3,"1-3 Days Late",IF(O240<=7,"4-7 Days Late","8+ Days Late"))) -> On Time/Early | U240: =IF(P240="Delayed","Needs Review","Normal") -> Normal | V240: https://www.kaggle.com/datasets/olistbr/brazilian-ecommerce
A241: cd6825309a436ed7785575f1ac55a38d | B241: 42892.873 | C241: 42892.924 | D241: 42894.616 | E241: 42898.724 | F241: 42906 | G241: SP | H241: Praia Grande | I241: Watches Gifts | J241: 1 | K241: 169.9 | L241: 8.77 | M241: 5 | N241: =IFERROR(E241-B241,"") -> 5.8514583 | O241: =IFERROR(MAX(0,E241-F241),"") -> 0 | P241: =IF(O241>0,"Delayed","On Time") -> On Time | Q241: =IFERROR((C241-B241)*24,"") -> 1.2255556 | R241: =IFERROR(D241-C241,"") -> 1.6919444 | S241: =IFERROR(E241-D241,"") -> 4.1084491 | T241: =IF(O241=0,"On Time/Early",IF(O241<=3,"1-3 Days Late",IF(O241<=7,"4-7 Days Late","8+ Days Late"))) -> On Time/Early | U241: =IF(P241="Delayed","Needs Review","Normal") -> Normal | V241: https://www.kaggle.com/datasets/olistbr/brazilian-ecommerce
A242: 276c37d3aa8872a9e3f7858b0fefa062 | B242: 42892.976 | C242: 42892.983 | D242: 42894.577 | E242: 42898.485 | F242: 42913 | G242: SP | H242: Marilia | I242: Sports Leisure | J242: 1 | K242: 113.9 | L242: 12.3 | M242: 5 | N242: =IFERROR(E242-B242,"") -> 5.5084028 | O242: =IFERROR(MAX(0,E242-F242),"") -> 0 | P242: =IF(O242>0,"Delayed","On Time") -> On Time | Q242: =IFERROR((C242-B242)*24,"") -> 0.16416667 | R242: =IFERROR(D242-C242,"") -> 1.5935995 | S242: =IFERROR(E242-D242,"") -> 3.907963 | T242: =IF(O242=0,"On Time/Early",IF(O242<=3,"1-3 Days Late",IF(O242<=7,"4-7 Days Late","8+ Days Late"))) -> On Time/Early | U242: =IF(P242="Delayed","Needs Review","Normal") -> Normal | V242: https://www.kaggle.com/datasets/olistbr/brazilian-ecommerce
A243: 22eed40bee218240dc8862ed7fcf4bb5 | B243: 42893.914 | C243: 42893.92 | D243: 42894.614 | E243: 42905.9 | F243: 42916 | G243: MG | H243: Teofilo Otoni | I243: Toys | J243: 1 | K243: 76.89 | L243: 16.3 | M243: 4 | N243: =IFERROR(E243-B243,"") -> 11.985718 | O243: =IFERROR(MAX(0,E243-F243),"") -> 0 | P243: =IF(O243>0,"Delayed","On Time") -> On Time | Q243: =IFERROR((C243-B243)*24,"") -> 0.1525 | R243: =IFERROR(D243-C243,"") -> 0.69336806 | S243: =IFERROR(E243-D243,"") -> 11.285995 | T243: =IF(O243=0,"On Time/Early",IF(O243<=3,"1-3 Days Late",IF(O243<=7,"4-7 Days Late","8+ Days Late"))) -> On Time/Early | U243: =IF(P243="Delayed","Needs Review","Normal") -> Normal | V243: https://www.kaggle.com/datasets/olistbr/brazilian-ecommerce
A244: 7b8b1e2fbbe6a726e3bd583956716bcb | B244: 42894.552 | C244: 42895.108 | D244: 42895.666 | E244: 42898.735 | F244: 42908 | G244: SP | H244: Sao Paulo | I244: Furniture Decor | J244: 1 | K244: 49.99 | L244: 9.34 | M244: 5 | N244: =IFERROR(E244-B244,"") -> 4.182581 | O244: =IFERROR(MAX(0,E244-F244),"") -> 0 | P244: =IF(O244>0,"Delayed","On Time") -> On Time | Q244: =IFERROR((C244-B244)*24,"") -> 13.338333 | R244: =IFERROR(D244-C244,"") -> 0.55851852 | S244: =IFERROR(E244-D244,"") -> 3.0682986 | T244: =IF(O244=0,"On Time/Early",IF(O244<=3,"1-3 Days Late",IF(O244<=7,"4-7 Days Late","8+ Days Late"))) -> On Time/Early | U244: =IF(P244="Delayed","Needs Review","Normal") -> Normal | V244: https://www.kaggle.com/datasets/olistbr/brazilian-ecommerce
A245: 8ddb4b28bb9d86ac2bfcc17f93c1161e | B245: 42894.915 | C245: 42894.924 | D245: 42895.59 | E245: 42907.72 | F245: 42919 | G245: SP | H245: Pedreira | I245: Auto | J245: 1 | K245: 155.75 | L245: 17.34 | M245: 4 | N245: =IFERROR(E245-B245,"") -> 12.805127 | O245: =IFERROR(MAX(0,E245-F245),"") -> 0 | P245: =IF(O245>0,"Delayed","On Time") -> On Time | Q245: =IFERROR((C245-B245)*24,"") -> 0.20166667 | R245: =IFERROR(D245-C245,"") -> 0.66631944 | S245: =IFERROR(E245-D245,"") -> 12.130405 | T245: =IF(O245=0,"On Time/Early",IF(O245<=3,"1-3 Days Late",IF(O245<=7,"4-7 Days Late","8+ Days Late"))) -> On Time/Early | U245: =IF(P245="Delayed","Needs Review","Normal") -> Normal | V245: https://www.kaggle.com/datasets/olistbr/brazilian-ecommerce
A246: aa2ae4efd578f1c304128a899e4d1a17 | B246: 42894.949 | C246: 42894.955 | D246: 42900.337 | E246: 42908.357 | F246: 42920 | G246: SC | H246: Garopaba | I246: Bed Bath Table | J246: 1 | K246: 338.5 | L246: 79.39 | M246: 5 | N246: =IFERROR(E246-B246,"") -> 13.408102 | O246: =IFERROR(MAX(0,E246-F246),"") -> 0 | P246: =IF(O246>0,"Delayed","On Time") -> On Time | Q246: =IFERROR((C246-B246)*24,"") -> 0.14583333 | R246: =IFERROR(D246-C246,"") -> 5.382037 | S246: =IFERROR(E246-D246,"") -> 8.0199884 | T246: =IF(O246=0,"On Time/Early",IF(O246<=3,"1-3 Days Late",IF(O246<=7,"4-7 Days Late","8+ Days Late"))) -> On Time/Early | U246: =IF(P246="Delayed","Needs Review","Normal") -> Normal | V246: https://www.kaggle.com/datasets/olistbr/brazilian-ecommerce
A247: 8dfcba64312b559340f9c9f65ac6205c | B247: 42895.242 | C247: 42896.128 | D247: 42898.296 | E247: 42905.518 | F247: 42920 | G247: MG | H247: Matozinhos | I247: Books Technical | J247: 1 | K247: 80 | L247: 15.32 | M247: 5 | N247: =IFERROR(E247-B247,"") -> 10.275949 | O247: =IFERROR(MAX(0,E247-F247),"") -> 0 | P247: =IF(O247>0,"Delayed","On Time") -> On Time | Q247: =IFERROR((C247-B247)*24,"") -> 21.249722 | R247: =IFERROR(D247-C247,"") -> 2.1684838 | S247: =IFERROR(E247-D247,"") -> 7.2220602 | T247: =IF(O247=0,"On Time/Early",IF(O247<=3,"1-3 Days Late",IF(O247<=7,"4-7 Days Late","8+ Days Late"))) -> On Time/Early | U247: =IF(P247="Delayed","Needs Review","Normal") -> Normal | V247: https://www.kaggle.com/datasets/olistbr/brazilian-ecommerce
A248: 1c4e3dcee9d5486d01d55a8db6d978d6 | B248: 42895.433 | C248: 42895.442 | D248: 42899.603 | E248: 42909.493 | F248: 42922 | G248: ES | H248: Aracruz | I248: Health Beauty | J248: 1 | K248: 119.9 | L248: 36.18 | M248: 4 | N248: =IFERROR(E248-B248,"") -> 14.059873 | O248: =IFERROR(MAX(0,E248-F248),"") -> 0 | P248: =IF(O248>0,"Delayed","On Time") -> On Time | Q248: =IFERROR((C248-B248)*24,"") -> 0.22972222 | R248: =IFERROR(D248-C248,"") -> 4.160544 | S248: =IFERROR(E248-D248,"") -> 9.8897569 | T248: =IF(O248=0,"On Time/Early",IF(O248<=3,"1-3 Days Late",IF(O248<=7,"4-7 Days Late","8+ Days Late"))) -> On Time/Early | U248: =IF(P248="Delayed","Needs Review","Normal") -> Normal | V248: https://www.kaggle.com/datasets/olistbr/brazilian-ecommerce
A249: 3ea37e479ca4fb57227d43b806c98174 | B249: 42895.508 | C249: 42895.546 | D249: 42895.609 | E249: 42900.594 | F249: 42919 | G249: SP | H249: Bauru | I249: Perfumery | J249: 1 | K249: 219.9 | L249: 13.04 | M249: 5 | N249: =IFERROR(E249-B249,"") -> 5.0860995 | O249: =IFERROR(MAX(0,E249-F249),"") -> 0 | P249: =IF(O249>0,"Delayed","On Time") -> On Time | Q249: =IFERROR((C249-B249)*24,"") -> 0.89527778 | R249: =IFERROR(D249-C249,"") -> 0.063877315 | S249: =IFERROR(E249-D249,"") -> 4.984919 | T249: =IF(O249=0,"On Time/Early",IF(O249<=3,"1-3 Days Late",IF(O249<=7,"4-7 Days Late","8+ Days Late"))) -> On Time/Early | U249: =IF(P249="Delayed","Needs Review","Normal") -> Normal | V249: https://www.kaggle.com/datasets/olistbr/brazilian-ecommerce
A250: 7ef7d4f03d667e9166770e61047606f3 | B250: 42895.995 | C250: 42896.008 | D250: 42898.382 | E250: 42909.458 | F250: 42930 | G250: MA | H250: Imperatriz | I250: Fashion Bags Accessories | J250: 1 | K250: 49 | L250: 34.15 | M250: 3 | N250: =IFERROR(E250-B250,"") -> 13.462743 | O250: =IFERROR(MAX(0,E250-F250),"") -> 0 | P250: =IF(O250>0,"Delayed","On Time") -> On Time | Q250: =IFERROR((C250-B250)*24,"") -> 0.29888889 | R250: =IFERROR(D250-C250,"") -> 2.3739352 | S250: =IFERROR(E250-D250,"") -> 11.076354 | T250: =IF(O250=0,"On Time/Early",IF(O250<=3,"1-3 Days Late",IF(O250<=7,"4-7 Days Late","8+ Days Late"))) -> On Time/Early | U250: =IF(P250="Delayed","Needs Review","Normal") -> Normal | V250: https://www.kaggle.com/datasets/olistbr/brazilian-ecommerce
A251: 76149a98fb53f831f6aa676c3193ee0f | B251: 42896.606 | C251: 42897.613 | D251: 42898.434 | E251: 42908.56 | F251: 42921 | G251: MG | H251: Alem Paraiba | I251: Market Place | J251: 1 | K251: 59.9 | L251: 15.17 | M251: 5 | N251: =IFERROR(E251-B251,"") -> 11.954398 | O251: =IFERROR(MAX(0,E251-F251),"") -> 0 | P251: =IF(O251>0,"Delayed","On Time") -> On Time | Q251: =IFERROR((C251-B251)*24,"") -> 24.163889 | R251: =IFERROR(D251-C251,"") -> 0.82086806 | S251: =IFERROR(E251-D251,"") -> 10.126701 | T251: =IF(O251=0,"On Time/Early",IF(O251<=3,"1-3 Days Late",IF(O251<=7,"4-7 Days Late","8+ Days Late"))) -> On Time/Early | U251: =IF(P251="Delayed","Needs Review","Normal") -> Normal | V251: https://www.kaggle.com/datasets/olistbr/brazilian-ecommerce
... A912: 61e5353969ba519689f085a0379fccda | B912: 43104.38 | C912: 43104.389 | D912: 43108.879 | E912: 43131.874 | F912: 43139 | G912: RJ | H912: Barra Do Pirai | I912: Furniture Decor | J912: 1 | K912: 69.9 | L912: 20.98 | M912: 5 | N912: =IFERROR(E912-B912,"") -> 27.493229 | O912: =IFERROR(MAX(0,E912-F912),"") -> 0 | P912: =IF(O912>0,"Delayed","On Time") -> On Time | Q912: =IFERROR((C912-B912)*24,"") -> 0.19472222 | R912: =IFERROR(D912-C912,"") -> 4.4904167 | S912: =IFERROR(E912-D912,"") -> 22.994699 | T912: =IF(O912=0,"On Time/Early",IF(O912<=3,"1-3 Days Late",IF(O912<=7,"4-7 Days Late","8+ Days Late"))) -> On Time/Early | U912: =IF(P912="Delayed","Needs Review","Normal") -> Normal | V912: https://www.kaggle.com/datasets/olistbr/brazilian-ecommerce
A913: 066fbbe8fc3345df85f0f1dc2ad03bce | B913: 43104.406 | C913: 43104.413 | D913: 43105.069 | E913: 43130.578 | F913: 43133 | G913: SP | H913: Campinas | I913: Baby | J913: 1 | K913: 26.9 | L913: 14.1 | N913: =IFERROR(E913-B913,"") -> 26.171933 | O913: =IFERROR(MAX(0,E913-F913),"") -> 0 | P913: =IF(O913>0,"Delayed","On Time") -> On Time | Q913: =IFERROR((C913-B913)*24,"") -> 0.1625 | R913: =IFERROR(D913-C913,"") -> 0.65579861 | S913: =IFERROR(E913-D913,"") -> 25.509363 | T913: =IF(O913=0,"On Time/Early",IF(O913<=3,"1-3 Days Late",IF(O913<=7,"4-7 Days Late","8+ Days Late"))) -> On Time/Early | U913: =IF(P913="Delayed","Needs Review","Normal") -> Normal | V913: https://www.kaggle.com/datasets/olistbr/brazilian-ecommerce
A914: 1f297fe93c435a51586ee198938876d3 | B914: 43104.623 | C914: 43104.631 | D914: 43105.849 | E914: 43119.123 | F914: 43129 | G914: SP | H914: Ubatuba | I914: Electronics | J914: 1 | K914: 18.9 | L914: 11.85 | M914: 5 | N914: =IFERROR(E914-B914,"") -> 14.500174 | O914: =IFERROR(MAX(0,E914-F914),"") -> 0 | P914: =IF(O914>0,"Delayed","On Time") -> On Time | Q914: =IFERROR((C914-B914)*24,"") -> 0.18222222 | R914: =IFERROR(D914-C914,"") -> 1.2179977 | S914: =IFERROR(E914-D914,"") -> 13.274583 | T914: =IF(O914=0,"On Time/Early",IF(O914<=3,"1-3 Days Late",IF(O914<=7,"4-7 Days Late","8+ Days Late"))) -> On Time/Early | U914: =IF(P914="Delayed","Needs Review","Normal") -> Normal | V914: https://www.kaggle.com/datasets/olistbr/brazilian-ecommerce
A915: 1fd00a38cb5caa89ca06e82069412d5f | B915: 43104.626 | C915: 43105.855 | D915: 43116.839 | E915: 43117.953 | F915: 43122 | G915: SP | H915: Sao Paulo | I915: Toys | J915: 1 | K915: 160 | L915: 12.33 | M915: 5 | N915: =IFERROR(E915-B915,"") -> 13.326736 | O915: =IFERROR(MAX(0,E915-F915),"") -> 0 | P915: =IF(O915>0,"Delayed","On Time") -> On Time | Q915: =IFERROR((C915-B915)*24,"") -> 29.498056 | R915: =IFERROR(D915-C915,"") -> 10.98441 | S915: =IFERROR(E915-D915,"") -> 1.1132407 | T915: =IF(O915=0,"On Time/Early",IF(O915<=3,"1-3 Days Late",IF(O915<=7,"4-7 Days Late","8+ Days Late"))) -> On Time/Early | U915: =IF(P915="Delayed","Needs Review","Normal") -> Normal | V915: https://www.kaggle.com/datasets/olistbr/brazilian-ecommerce
A916: 567d581c34bed9ac50925ac1dc53b0c5 | B916: 43104.652 | C916: 43104.659 | D916: 43108.776 | E916: 43119.728 | F916: 43136 | G916: ES | H916: Vargem Alta | I916: Stationery | J916: 1 | K916: 129 | L916: 18.15 | M916: 5 | N916: =IFERROR(E916-B916,"") -> 15.076065 | O916: =IFERROR(MAX(0,E916-F916),"") -> 0 | P916: =IF(O916>0,"Delayed","On Time") -> On Time | Q916: =IFERROR((C916-B916)*24,"") -> 0.15444444 | R916: =IFERROR(D916-C916,"") -> 4.1175926 | S916: =IFERROR(E916-D916,"") -> 10.952037 | T916: =IF(O916=0,"On Time/Early",IF(O916<=3,"1-3 Days Late",IF(O916<=7,"4-7 Days Late","8+ Days Late"))) -> On Time/Early | U916: =IF(P916="Delayed","Needs Review","Normal") -> Normal | V916: https://www.kaggle.com/datasets/olistbr/brazilian-ecommerce
A917: 4c8ea2a4ee7b1d91b837360ccb23fe89 | B917: 43104.688 | C917: 43104.7 | D917: 43110.693 | E917: 43131.661 | F917: 43136 | G917: SC | H917: Gaspar | I917: Small Appliances | J917: 1 | K917: 193 | L917: 15.08 | M917: 5 | N917: =IFERROR(E917-B917,"") -> 26.973067 | O917: =IFERROR(MAX(0,E917-F917),"") -> 0 | P917: =IF(O917>0,"Delayed","On Time") -> On Time | Q917: =IFERROR((C917-B917)*24,"") -> 0.28527778 | R917: =IFERROR(D917-C917,"") -> 5.993588 | S917: =IFERROR(E917-D917,"") -> 20.967593 | T917: =IF(O917=0,"On Time/Early",IF(O917<=3,"1-3 Days Late",IF(O917<=7,"4-7 Days Late","8+ Days Late"))) -> On Time/Early | U917: =IF(P917="Delayed","Needs Review","Normal") -> Normal | V917: https://www.kaggle.com/datasets/olistbr/brazilian-ecommerce
A918: 11b92cb31ef70accdf3705f879a0a891 | B918: 43104.71 | C918: 43104.718 | D918: 43110.837 | E918: 43112.929 | F918: 43122 | G918: SP | H918: Sao Paulo | I918: Drinks | J918: 1 | K918: 39.49 | L918: 8.27 | M918: 3 | N918: =IFERROR(E918-B918,"") -> 8.2189931 | O918: =IFERROR(MAX(0,E918-F918),"") -> 0 | P918: =IF(O918>0,"Delayed","On Time") -> On Time | Q918: =IFERROR((C918-B918)*24,"") -> 0.19027778 | R918: =IFERROR(D918-C918,"") -> 6.1192361 | S918: =IFERROR(E918-D918,"") -> 2.0918287 | T918: =IF(O918=0,"On Time/Early",IF(O918<=3,"1-3 Days Late",IF(O918<=7,"4-7 Days Late","8+ Days Late"))) -> On Time/Early | U918: =IF(P918="Delayed","Needs Review","Normal") -> Normal | V918: https://www.kaggle.com/datasets/olistbr/brazilian-ecommerce
A919: 90c7f72cacf60b2a63da77187689e3d1 | B919: 43104.763 | C919: 43106.089 | D919: 43110.56 | E919: 43112.932 | F919: 43129 | G919: SP | H919: Americana | I919: Stationery | J919: 1 | K919: 129 | L919: 13.92 | M919: 4 | N919: =IFERROR(E919-B919,"") -> 8.168912 | O919: =IFERROR(MAX(0,E919-F919),"") -> 0 | P919: =IF(O919>0,"Delayed","On Time") -> On Time | Q919: =IFERROR((C919-B919)*24,"") -> 31.834167 | R919: =IFERROR(D919-C919,"") -> 4.4700694 | S919: =IFERROR(E919-D919,"") -> 2.372419 | T919: =IF(O919=0,"On Time/Early",IF(O919<=3,"1-3 Days Late",IF(O919<=7,"4-7 Days Late","8+ Days Late"))) -> On Time/Early | U919: =IF(P919="Delayed","Needs Review","Normal") -> Normal | V919: https://www.kaggle.com/datasets/olistbr/brazilian-ecommerce
A920: 2f41dbe3e1e76b3d8092ff2bd3ea676f | B920: 43104.805 | C920: 43104.811 | D920: 43105.849 | E920: 43113.008 | F920: 43133 | G920: PR | H920: Sao Miguel Do Iguacu | I920: Electronics | J920: 1 | K920: 18.9 | L920: 15.1 | M920: 5 | N920: =IFERROR(E920-B920,"") -> 8.2035301 | O920: =IFERROR(MAX(0,E920-F920),"") -> 0 | P920: =IF(O920>0,"Delayed","On Time") -> On Time | Q920: =IFERROR((C920-B920)*24,"") -> 0.15027778 | R920: =IFERROR(D920-C920,"") -> 1.0376852 | S920: =IFERROR(E920-D920,"") -> 7.1595833 | T920: =IF(O920=0,"On Time/Early",IF(O920<=3,"1-3 Days Late",IF(O920<=7,"4-7 Days Late","8+ Days Late"))) -> On Time/Early | U920: =IF(P920="Delayed","Needs Review","Normal") -> Normal | V920: https://www.kaggle.com/datasets/olistbr/brazilian-ecommerce
A921: 53f2d5cbef0a11dae2982bf04a35e121 | B921: 43105.894 | C921: 43105.9 | D921: 43109.902 | E921: 43113.069 | F921: 43133 | G921: SP | H921: Sao Paulo | I921: Luggage Accessories | J921: 1 | K921: 129.99 | L921: 17.16 | M921: 5 | N921: =IFERROR(E921-B921,"") -> 7.1743981 | O921: =IFERROR(MAX(0,E921-F921),"") -> 0 | P921: =IF(O921>0,"Delayed","On Time") -> On Time | Q921: =IFERROR((C921-B921)*24,"") -> 0.12444444 | R921: =IFERROR(D921-C921,"") -> 4.0020023 | S921: =IFERROR(E921-D921,"") -> 3.1672106 | T921: =IF(O921=0,"On Time/Early",IF(O921<=3,"1-3 Days Late",IF(O921<=7,"4-7 Days Late","8+ Days Late"))) -> On Time/Early | U921: =IF(P921="Delayed","Needs Review","Normal") -> Normal | V921: https://www.kaggle.com/datasets/olistbr/brazilian-ecommerce
A922: abfbbd144a437c6a51564ea668aab4b6 | B922: 43106.366 | C922: 43109.307 | D922: 43111.821 | E922: 43116.541 | F922: 43131 | G922: SP | H922: Campina Do Monte Alegre | I922: Pet Shop | J922: 1 | K922: 119 | L922: 40.82 | M922: 5 | N922: =IFERROR(E922-B922,"") -> 10.174931 | O922: =IFERROR(MAX(0,E922-F922),"") -> 0 | P922: =IF(O922>0,"Delayed","On Time") -> On Time | Q922: =IFERROR((C922-B922)*24,"") -> 70.590556 | R922: =IFERROR(D922-C922,"") -> 2.5138194 | S922: =IFERROR(E922-D922,"") -> 4.719838 | T922: =IF(O922=0,"On Time/Early",IF(O922<=3,"1-3 Days Late",IF(O922<=7,"4-7 Days Late","8+ Days Late"))) -> On Time/Early | U922: =IF(P922="Delayed","Needs Review","Normal") -> Normal | V922: https://www.kaggle.com/datasets/olistbr/brazilian-ecommerce
A923: 03c83b31dbc387f83f1b5579b53182fb | B923: 43106.667 | C923: 43109.31 | D923: 43109.985 | E923: 43117.837 | F923: 43137 | G923: MG | H923: Mariana | I923: Computers | J923: 1 | K923: 599 | L923: 73.41 | M923: 5 | N923: =IFERROR(E923-B923,"") -> 11.169317 | O923: =IFERROR(MAX(0,E923-F923),"") -> 0 | P923: =IF(O923>0,"Delayed","On Time") -> On Time | Q923: =IFERROR((C923-B923)*24,"") -> 63.430278 | R923: =IFERROR(D923-C923,"") -> 0.6750463 | S923: =IFERROR(E923-D923,"") -> 7.8513426 | T923: =IF(O923=0,"On Time/Early",IF(O923<=3,"1-3 Days Late",IF(O923<=7,"4-7 Days Late","8+ Days Late"))) -> On Time/Early | U923: =IF(P923="Delayed","Needs Review","Normal") -> Normal | V923: https://www.kaggle.com/datasets/olistbr/brazilian-ecommerce
A924: 353fcb9f0aa5bfdba9d0f676bdc044f3 | B924: 43106.95 | C924: 43106.955 | D924: 43109.792 | E924: 43129.916 | F924: 43132 | G924: SP | H924: Sao Paulo | I924: Furniture Decor | J924: 1 | K924: 49 | L924: 14.1 | M924: 3 | N924: =IFERROR(E924-B924,"") -> 22.966447 | O924: =IFERROR(MAX(0,E924-F924),"") -> 0 | P924: =IF(O924>0,"Delayed","On Time") -> On Time | Q924: =IFERROR((C924-B924)*24,"") -> 0.12333333 | R924: =IFERROR(D924-C924,"") -> 2.8365856 | S924: =IFERROR(E924-D924,"") -> 20.124722 | T924: =IF(O924=0,"On Time/Early",IF(O924<=3,"1-3 Days Late",IF(O924<=7,"4-7 Days Late","8+ Days Late"))) -> On Time/Early | U924: =IF(P924="Delayed","Needs Review","Normal") -> Normal | V924: https://www.kaggle.com/datasets/olistbr/brazilian-ecommerce
A925: f1f595bed1ee64a492e47dfdd7306983 | B925: 43107.431 | C925: 43107.437 | D925: 43109.002 | E925: 43123.712 | F925: 43140 | G925: RJ | H925: Niteroi | I925: Perfumery | J925: 1 | K925: 98 | L925: 36.01 | M925: 5 | N925: =IFERROR(E925-B925,"") -> 16.28059 | O925: =IFERROR(MAX(0,E925-F925),"") -> 0 | P925: =IF(O925>0,"Delayed","On Time") -> On Time | Q925: =IFERROR((C925-B925)*24,"") -> 0.13777778 | R925: =IFERROR(D925-C925,"") -> 1.5652894 | S925: =IFERROR(E925-D925,"") -> 14.70956 | T925: =IF(O925=0,"On Time/Early",IF(O925<=3,"1-3 Days Late",IF(O925<=7,"4-7 Days Late","8+ Days Late"))) -> On Time/Early | U925: =IF(P925="Delayed","Needs Review","Normal") -> Normal | V925: https://www.kaggle.com/datasets/olistbr/brazilian-ecommerce
... A1067: 7158a97d6f769b92be9b76bbcf8a48eb | B1067: 43134.855 | C1067: 43134.868 | D1067: 43139.861 | E1067: 43153.916 | F1067: 43161 | G1067: RJ | H1067: Rio De Janeiro | I1067: Home Appliances | J1067: 1 | K1067: 69.9 | L1067: 17.74 | M1067: 5 | N1067: =IFERROR(E1067-B1067,"") -> 19.060637 | O1067: =IFERROR(MAX(0,E1067-F1067),"") -> 0 | P1067: =IF(O1067>0,"Delayed","On Time") -> On Time | Q1067: =IFERROR((C1067-B1067)*24,"") -> 0.30722222 | R1067: =IFERROR(D1067-C1067,"") -> 4.9924421 | S1067: =IFERROR(E1067-D1067,"") -> 14.055394 | T1067: =IF(O1067=0,"On Time/Early",IF(O1067<=3,"1-3 Days Late",IF(O1067<=7,"4-7 Days Late","8+ Days Late"))) -> On Time/Early | U1067: =IF(P1067="Delayed","Needs Review","Normal") -> Normal | V1067: https://www.kaggle.com/datasets/olistbr/brazilian-ecommerce
A1068: 66b04218fe3a0af6ca54d243ecfb3737 | B1068: 43134.906 | C1068: 43134.913 | D1068: 43147.711 | E1068: 43157.583 | F1068: 43179 | G1068: ES | H1068: Rio Novo Do Sul | I1068: Computers Accessories | J1068: 1 | K1068: 27.9 | L1068: 16.79 | N1068: =IFERROR(E1068-B1068,"") -> 22.676748 | O1068: =IFERROR(MAX(0,E1068-F1068),"") -> 0 | P1068: =IF(O1068>0,"Delayed","On Time") -> On Time | Q1068: =IFERROR((C1068-B1068)*24,"") -> 0.18277778 | R1068: =IFERROR(D1068-C1068,"") -> 12.797593 | S1068: =IFERROR(E1068-D1068,"") -> 9.8715394 | T1068: =IF(O1068=0,"On Time/Early",IF(O1068<=3,"1-3 Days Late",IF(O1068<=7,"4-7 Days Late","8+ Days Late"))) -> On Time/Early | U1068: =IF(P1068="Delayed","Needs Review","Normal") -> Normal | V1068: https://www.kaggle.com/datasets/olistbr/brazilian-ecommerce
A1069: c7695e0fa70ef0373d4eaa6b11a4a6ef | B1069: 43135.924 | C1069: 43135.937 | D1069: 43138.984 | E1069: 43140.881 | F1069: 43157 | G1069: SP | H1069: Santos | I1069: Computers Accessories | J1069: 1 | K1069: 180 | L1069: 10.01 | M1069: 4 | N1069: =IFERROR(E1069-B1069,"") -> 4.9566319 | O1069: =IFERROR(MAX(0,E1069-F1069),"") -> 0 | P1069: =IF(O1069>0,"Delayed","On Time") -> On Time | Q1069: =IFERROR((C1069-B1069)*24,"") -> 0.3075 | R1069: =IFERROR(D1069-C1069,"") -> 3.0468171 | S1069: =IFERROR(E1069-D1069,"") -> 1.8970023 | T1069: =IF(O1069=0,"On Time/Early",IF(O1069<=3,"1-3 Days Late",IF(O1069<=7,"4-7 Days Late","8+ Days Late"))) -> On Time/Early | U1069: =IF(P1069="Delayed","Needs Review","Normal") -> Normal | V1069: https://www.kaggle.com/datasets/olistbr/brazilian-ecommerce
A1070: 8cfc6624adef5f59e3ddd7167bc07107 | B1070: 43136.435 | C1070: 43136.451 | D1070: 43137.947 | E1070: 43150.719 | F1070: 43161 | G1070: PR | H1070: Curitiba | I1070: Electronics | J1070: 1 | K1070: 13.65 | L1070: 14.1 | M1070: 5 | N1070: =IFERROR(E1070-B1070,"") -> 14.283576 | O1070: =IFERROR(MAX(0,E1070-F1070),"") -> 0 | P1070: =IF(O1070>0,"Delayed","On Time") -> On Time | Q1070: =IFERROR((C1070-B1070)*24,"") -> 0.38777778 | R1070: =IFERROR(D1070-C1070,"") -> 1.4951273 | S1070: =IFERROR(E1070-D1070,"") -> 12.772292 | T1070: =IF(O1070=0,"On Time/Early",IF(O1070<=3,"1-3 Days Late",IF(O1070<=7,"4-7 Days Late","8+ Days Late"))) -> On Time/Early | U1070: =IF(P1070="Delayed","Needs Review","Normal") -> Normal | V1070: https://www.kaggle.com/datasets/olistbr/brazilian-ecommerce
A1071: 06a9ff8c19b2d371a45c48568283929b | B1071: 43136.472 | C1071: 43136.483 | D1071: 43139.794 | E1071: 43146.744 | F1071: 43165 | G1071: BA | H1071: Salvador | I1071: Bed Bath Table | J1071: 1 | K1071: 32.2 | L1071: 16.92 | M1071: 5 | N1071: =IFERROR(E1071-B1071,"") -> 10.271736 | O1071: =IFERROR(MAX(0,E1071-F1071),"") -> 0 | P1071: =IF(O1071>0,"Delayed","On Time") -> On Time | Q1071: =IFERROR((C1071-B1071)*24,"") -> 0.27194444 | R1071: =IFERROR(D1071-C1071,"") -> 3.3109491 | S1071: =IFERROR(E1071-D1071,"") -> 6.949456 | T1071: =IF(O1071=0,"On Time/Early",IF(O1071<=3,"1-3 Days Late",IF(O1071<=7,"4-7 Days Late","8+ Days Late"))) -> On Time/Early | U1071: =IF(P1071="Delayed","Needs Review","Normal") -> Normal | V1071: https://www.kaggle.com/datasets/olistbr/brazilian-ecommerce
A1072: dfa82c0d8cadaa36975ca3f856251e6c | B1072: 43136.585 | C1072: 43136.594 | D1072: 43137.986 | E1072: 43139.516 | F1072: 43161 | G1072: SP | H1072: Taquaritinga | I1072: Sports Leisure | J1072: 1 | K1072: 107 | L1072: 12.25 | M1072: 5 | N1072: =IFERROR(E1072-B1072,"") -> 2.9314005 | O1072: =IFERROR(MAX(0,E1072-F1072),"") -> 0 | P1072: =IF(O1072>0,"Delayed","On Time") -> On Time | Q1072: =IFERROR((C1072-B1072)*24,"") -> 0.22444444 | R1072: =IFERROR(D1072-C1072,"") -> 1.3923611 | S1072: =IFERROR(E1072-D1072,"") -> 1.5296875 | T1072: =IF(O1072=0,"On Time/Early",IF(O1072<=3,"1-3 Days Late",IF(O1072<=7,"4-7 Days Late","8+ Days Late"))) -> On Time/Early | U1072: =IF(P1072="Delayed","Needs Review","Normal") -> Normal | V1072: https://www.kaggle.com/datasets/olistbr/brazilian-ecommerce
A1073: 53299baecd9869c74d5c439dc4078eec | B1073: 43136.615 | C1073: 43136.622 | D1073: 43139.825 | E1073: 43150.441 | F1073: 43164 | G1073: PR | H1073: Curitiba | I1073: Pet Shop | J1073: 1 | K1073: 105 | L1073: 22.6 | M1073: 5 | N1073: =IFERROR(E1073-B1073,"") -> 13.825579 | O1073: =IFERROR(MAX(0,E1073-F1073),"") -> 0 | P1073: =IF(O1073>0,"Delayed","On Time") -> On Time | Q1073: =IFERROR((C1073-B1073)*24,"") -> 0.15694444 | R1073: =IFERROR(D1073-C1073,"") -> 3.2028935 | S1073: =IFERROR(E1073-D1073,"") -> 10.616146 | T1073: =IF(O1073=0,"On Time/Early",IF(O1073<=3,"1-3 Days Late",IF(O1073<=7,"4-7 Days Late","8+ Days Late"))) -> On Time/Early | U1073: =IF(P1073="Delayed","Needs Review","Normal") -> Normal | V1073: https://www.kaggle.com/datasets/olistbr/brazilian-ecommerce
A1074: d3aae1141577275792d2c2b724f49819 | B1074: 43136.748 | C1074: 43136.761 | D1074: 43137.898 | E1074: 43139.13 | F1074: 43152 | G1074: SP | H1074: Santo Andre | I1074: Unknown | J1074: 1 | K1074: 157.77 | L1074: 9.3 | M1074: 1 | N1074: =IFERROR(E1074-B1074,"") -> 2.3822106 | O1074: =IFERROR(MAX(0,E1074-F1074),"") -> 0 | P1074: =IF(O1074>0,"Delayed","On Time") -> On Time | Q1074: =IFERROR((C1074-B1074)*24,"") -> 0.30777778 | R1074: =IFERROR(D1074-C1074,"") -> 1.1372569 | S1074: =IFERROR(E1074-D1074,"") -> 1.2321296 | T1074: =IF(O1074=0,"On Time/Early",IF(O1074<=3,"1-3 Days Late",IF(O1074<=7,"4-7 Days Late","8+ Days Late"))) -> On Time/Early | U1074: =IF(P1074="Delayed","Needs Review","Normal") -> Normal | V1074: https://www.kaggle.com/datasets/olistbr/brazilian-ecommerce
A1075: 3b8a6f4c963d2e04b3d7a0bb8dc84b6e | B1075: 43136.886 | C1075: 43137.691 | D1075: 43138.724 | E1075: 43149.618 | F1075: 43165 | G1075: SP | H1075: Sao Paulo | I1075: Bed Bath Table | J1075: 1 | K1075: 39.99 | L1075: 11.85 | M1075: 4 | N1075: =IFERROR(E1075-B1075,"") -> 12.731597 | O1075: =IFERROR(MAX(0,E1075-F1075),"") -> 0 | P1075: =IF(O1075>0,"Delayed","On Time") -> On Time | Q1075: =IFERROR((C1075-B1075)*24,"") -> 19.321111 | R1075: =IFERROR(D1075-C1075,"") -> 1.0324537 | S1075: =IFERROR(E1075-D1075,"") -> 10.894097 | T1075: =IF(O1075=0,"On Time/Early",IF(O1075<=3,"1-3 Days Late",IF(O1075<=7,"4-7 Days Late","8+ Days Late"))) -> On Time/Early | U1075: =IF(P1075="Delayed","Needs Review","Normal") -> Normal | V1075: https://www.kaggle.com/datasets/olistbr/brazilian-ecommerce
A1076: d226c6a38313ae07e11b12bad9adb222 | B1076: 43136.975 | C1076: 43136.983 | D1076: 43138.832 | E1076: 43151.656 | F1076: 43166 | G1076: PE | H1076: Recife | I1076: Health Beauty | J1076: 1 | K1076: 46.9 | L1076: 21.15 | M1076: 3 | N1076: =IFERROR(E1076-B1076,"") -> 14.681354 | O1076: =IFERROR(MAX(0,E1076-F1076),"") -> 0 | P1076: =IF(O1076>0,"Delayed","On Time") -> On Time | Q1076: =IFERROR((C1076-B1076)*24,"") -> 0.18916667 | R1076: =IFERROR(D1076-C1076,"") -> 1.8489236 | S1076: =IFERROR(E1076-D1076,"") -> 12.824549 | T1076: =IF(O1076=0,"On Time/Early",IF(O1076<=3,"1-3 Days Late",IF(O1076<=7,"4-7 Days Late","8+ Days Late"))) -> On Time/Early | U1076: =IF(P1076="Delayed","Needs Review","Normal") -> Normal | V1076: https://www.kaggle.com/datasets/olistbr/brazilian-ecommerce
A1077: ba8dd052f0697464c9b19669d50cf248 | B1077: 43137.352 | C1077: 43137.368 | D1077: 43137.822 | E1077: 43139.659 | F1077: 43164 | G1077: MG | H1077: Pedro Leopoldo | I1077: Auto | J1077: 1 | K1077: 19 | L1077: 14.1 | M1077: 5 | N1077: =IFERROR(E1077-B1077,"") -> 2.306794 | O1077: =IFERROR(MAX(0,E1077-F1077),"") -> 0 | P1077: =IF(O1077>0,"Delayed","On Time") -> On Time | Q1077: =IFERROR((C1077-B1077)*24,"") -> 0.37472222 | R1077: =IFERROR(D1077-C1077,"") -> 0.45393519 | S1077: =IFERROR(E1077-D1077,"") -> 1.8372454 | T1077: =IF(O1077=0,"On Time/Early",IF(O1077<=3,"1-3 Days Late",IF(O1077<=7,"4-7 Days Late","8+ Days Late"))) -> On Time/Early | U1077: =IF(P1077="Delayed","Needs Review","Normal") -> Normal | V1077: https://www.kaggle.com/datasets/olistbr/brazilian-ecommerce
A1078: 19cf1ad54fe41157e76ef5f1fc4eb56f | B1078: 43137.413 | C1078: 43137.425 | D1078: 43137.912 | E1078: 43150.609 | F1078: 43167 | G1078: GO | H1078: Goias | I1078: Bed Bath Table | J1078: 1 | K1078: 43.92 | L1078: 20.84 | M1078: 5 | N1078: =IFERROR(E1078-B1078,"") -> 13.196632 | O1078: =IFERROR(MAX(0,E1078-F1078),"") -> 0 | P1078: =IF(O1078>0,"Delayed","On Time") -> On Time | Q1078: =IFERROR((C1078-B1078)*24,"") -> 0.29305556 | R1078: =IFERROR(D1078-C1078,"") -> 0.48722222 | S1078: =IFERROR(E1078-D1078,"") -> 12.697199 | T1078: =IF(O1078=0,"On Time/Early",IF(O1078<=3,"1-3 Days Late",IF(O1078<=7,"4-7 Days Late","8+ Days Late"))) -> On Time/Early | U1078: =IF(P1078="Delayed","Needs Review","Normal") -> Normal | V1078: https://www.kaggle.com/datasets/olistbr/brazilian-ecommerce
A1079: f322d0eb62f5e70fa62f78ae2b6d5ee0 | B1079: 43137.534 | C1079: 43138.12 | D1079: 43139.028 | E1079: 43155.717 | F1079: 43164 | G1079: MG | H1079: Itabira | I1079: Housewares | J1079: 1 | K1079: 265 | L1079: 23.99 | M1079: 2 | N1079: =IFERROR(E1079-B1079,"") -> 18.182766 | O1079: =IFERROR(MAX(0,E1079-F1079),"") -> 0 | P1079: =IF(O1079>0,"Delayed","On Time") -> On Time | Q1079: =IFERROR((C1079-B1079)*24,"") -> 14.047778 | R1079: =IFERROR(D1079-C1079,"") -> 0.90815972 | S1079: =IFERROR(E1079-D1079,"") -> 16.689282 | T1079: =IF(O1079=0,"On Time/Early",IF(O1079<=3,"1-3 Days Late",IF(O1079<=7,"4-7 Days Late","8+ Days Late"))) -> On Time/Early | U1079: =IF(P1079="Delayed","Needs Review","Normal") -> Normal | V1079: https://www.kaggle.com/datasets/olistbr/brazilian-ecommerce
A1080: fc5850037cf5ed63407d1c26885ba778 | B1080: 43137.648 | C1080: 43137.675 | D1080: 43139.884 | E1080: 43140.838 | F1080: 43168 | G1080: SP | H1080: Sao Carlos | I1080: Housewares | J1080: 1 | K1080: 22.99 | L1080: 13.37 | M1080: 4 | N1080: =IFERROR(E1080-B1080,"") -> 3.19 | O1080: =IFERROR(MAX(0,E1080-F1080),"") -> 0 | P1080: =IF(O1080>0,"Delayed","On Time") -> On Time | Q1080: =IFERROR((C1080-B1080)*24,"") -> 0.635 | R1080: =IFERROR(D1080-C1080,"") -> 2.2086806 | S1080: =IFERROR(E1080-D1080,"") -> 0.95486111 | T1080: =IF(O1080=0,"On Time/Early",IF(O1080<=3,"1-3 Days Late",IF(O1080<=7,"4-7 Days Late","8+ Days Late"))) -> On Time/Early | U1080: =IF(P1080="Delayed","Needs Review","Normal") -> Normal | V1080: https://www.kaggle.com/datasets/olistbr/brazilian-ecommerce
... A1092: a04b6ad9c324577c000835fca4587931 | B1092: 43139.363 | C1092: 43140.118 | D1092: 43150.632 | E1092: 43158.786 | F1092: 43166 | G1092: SP | H1092: Paulinia | I1092: Computers Accessories | J1092: 2 | K1092: 553.78 | L1092: 38.38 | M1092: 2 | N1092: =IFERROR(E1092-B1092,"") -> 19.422454 | O1092: =IFERROR(MAX(0,E1092-F1092),"") -> 0 | P1092: =IF(O1092>0,"Delayed","On Time") -> On Time | Q1092: =IFERROR((C1092-B1092)*24,"") -> 18.125556 | R1092: =IFERROR(D1092-C1092,"") -> 10.513079 | S1092: =IFERROR(E1092-D1092,"") -> 8.1541435 | T1092: =IF(O1092=0,"On Time/Early",IF(O1092<=3,"1-3 Days Late",IF(O1092<=7,"4-7 Days Late","8+ Days Late"))) -> On Time/Early | U1092: =IF(P1092="Delayed","Needs Review","Normal") -> Normal | V1092: https://www.kaggle.com/datasets/olistbr/brazilian-ecommerce
A1093: 1591f1de66fc6657c009d107db35c4d2 | B1093: 43139.822 | C1093: 43139.83 | D1093: 43145.646 | E1093: 43155.579 | F1093: 43166 | G1093: RJ | H1093: Rio De Janeiro | I1093: Baby | J1093: 1 | K1093: 24.99 | L1093: 17.92 | N1093: =IFERROR(E1093-B1093,"") -> 15.757095 | O1093: =IFERROR(MAX(0,E1093-F1093),"") -> 0 | P1093: =IF(O1093>0,"Delayed","On Time") -> On Time | Q1093: =IFERROR((C1093-B1093)*24,"") -> 0.20361111 | R1093: =IFERROR(D1093-C1093,"") -> 5.8161806 | S1093: =IFERROR(E1093-D1093,"") -> 9.9324306 | T1093: =IF(O1093=0,"On Time/Early",IF(O1093<=3,"1-3 Days Late",IF(O1093<=7,"4-7 Days Late","8+ Days Late"))) -> On Time/Early | U1093: =IF(P1093="Delayed","Needs Review","Normal") -> Normal | V1093: https://www.kaggle.com/datasets/olistbr/brazilian-ecommerce
A1094: 953e1e0627386608dd2ac2670d72950f | B1094: 43139.973 | C1094: 43139.983 | D1094: 43140.784 | E1094: 43145.785 | F1094: 43153 | G1094: SP | H1094: Sao Paulo | I1094: Furniture Decor | J1094: 2 | K1094: 109.8 | L1094: 17.44 | M1094: 5 | N1094: =IFERROR(E1094-B1094,"") -> 5.8120023 | O1094: =IFERROR(MAX(0,E1094-F1094),"") -> 0 | P1094: =IF(O1094>0,"Delayed","On Time") -> On Time | Q1094: =IFERROR((C1094-B1094)*24,"") -> 0.25111111 | R1094: =IFERROR(D1094-C1094,"") -> 0.80063657 | S1094: =IFERROR(E1094-D1094,"") -> 5.0009028 | T1094: =IF(O1094=0,"On Time/Early",IF(O1094<=3,"1-3 Days Late",IF(O1094<=7,"4-7 Days Late","8+ Days Late"))) -> On Time/Early | U1094: =IF(P1094="Delayed","Needs Review","Normal") -> Normal | V1094: https://www.kaggle.com/datasets/olistbr/brazilian-ecommerce
A1095: 1162cd6cea2c1d4d79492aef88f50618 | B1095: 43140.29 | C1095: 43140.302 | D1095: 43145.745 | E1095: 43166.762 | F1095: 43166 | G1095: PR | H1095: Toledo | I1095: Housewares | J1095: 2 | K1095: 339.98 | L1095: 33.9 | M1095: 5 | N1095: =IFERROR(E1095-B1095,"") -> 26.472072 | O1095: =IFERROR(MAX(0,E1095-F1095),"") -> 0.7622338 | P1095: =IF(O1095>0,"Delayed","On Time") -> Delayed | Q1095: =IFERROR((C1095-B1095)*24,"") -> 0.29111111 | R1095: =IFERROR(D1095-C1095,"") -> 5.4423843 | S1095: =IFERROR(E1095-D1095,"") -> 21.017558 | T1095: =IF(O1095=0,"On Time/Early",IF(O1095<=3,"1-3 Days Late",IF(O1095<=7,"4-7 Days Late","8+ Days Late"))) -> 1-3 Days Late | U1095: =IF(P1095="Delayed","Needs Review","Normal") -> Needs Review | V1095: https://www.kaggle.com/datasets/olistbr/brazilian-ecommerce
A1096: bc057cb666f536dffa89e882573a1ff0 | B1096: 43140.703 | C1096: 43140.715 | D1096: 43146.999 | E1096: 43150.695 | F1096: 43160 | G1096: SP | H1096: Sao Paulo | I1096: Fixed Telephony | J1096: 1 | K1096: 90 | L1096: 8.37 | M1096: 1 | N1096: =IFERROR(E1096-B1096,"") -> 9.9914236 | O1096: =IFERROR(MAX(0,E1096-F1096),"") -> 0 | P1096: =IF(O1096>0,"Delayed","On Time") -> On Time | Q1096: =IFERROR((C1096-B1096)*24,"") -> 0.28611111 | R1096: =IFERROR(D1096-C1096,"") -> 6.2842245 | S1096: =IFERROR(E1096-D1096,"") -> 3.6952778 | T1096: =IF(O1096=0,"On Time/Early",IF(O1096<=3,"1-3 Days Late",IF(O1096<=7,"4-7 Days Late","8+ Days Late"))) -> On Time/Early | U1096: =IF(P1096="Delayed","Needs Review","Normal") -> Normal | V1096: https://www.kaggle.com/datasets/olistbr/brazilian-ecommerce
A1097: 6cd2700e3e9fc015e3bbe4ee264af57b | B1097: 43140.734 | C1097: 43140.743 | D1097: 43145.687 | E1097: 43153.804 | F1097: 43167 | G1097: RJ | H1097: Rio De Janeiro | I1097: Computers Accessories | J1097: 1 | K1097: 44.9 | L1097: 16.79 | M1097: 1 | N1097: =IFERROR(E1097-B1097,"") -> 13.070174 | O1097: =IFERROR(MAX(0,E1097-F1097),"") -> 0 | P1097: =IF(O1097>0,"Delayed","On Time") -> On Time | Q1097: =IFERROR((C1097-B1097)*24,"") -> 0.23083333 | R1097: =IFERROR(D1097-C1097,"") -> 4.9434028 | S1097: =IFERROR(E1097-D1097,"") -> 8.1171528 | T1097: =IF(O1097=0,"On Time/Early",IF(O1097<=3,"1-3 Days Late",IF(O1097<=7,"4-7 Days Late","8+ Days Late"))) -> On Time/Early | U1097: =IF(P1097="Delayed","Needs Review","Normal") -> Normal | V1097: https://www.kaggle.com/datasets/olistbr/brazilian-ecommerce
A1098: beebcdb81ca8d717ee63fbee85b1826e | B1098: 43140.938 | C1098: 43146.161 | D1098: 43150.551 | E1098: 43215.914 | F1098: 43167 | G1098: CE | H1098: Fortaleza | I1098: Telephony | J1098: 1 | K1098: 18.98 | L1098: 17.63 | M1098: 1 | N1098: =IFERROR(E1098-B1098,"") -> 74.976794 | O1098: =IFERROR(MAX(0,E1098-F1098),"") -> 48.914375 | P1098: =IF(O1098>0,"Delayed","On Time") -> Delayed | Q1098: =IFERROR((C1098-B1098)*24,"") -> 125.35528 | R1098: =IFERROR(D1098-C1098,"") -> 4.3904167 | S1098: =IFERROR(E1098-D1098,"") -> 65.363241 | T1098: =IF(O1098=0,"On Time/Early",IF(O1098<=3,"1-3 Days Late",IF(O1098<=7,"4-7 Days Late","8+ Days Late"))) -> 8+ Days Late | U1098: =IF(P1098="Delayed","Needs Review","Normal") -> Needs Review | V1098: https://www.kaggle.com/datasets/olistbr/brazilian-ecommerce
...

Sheet Monthly_Analysis
A1: Monthly Delivery Performance Analysis
A2: Analysis calculated from the full delivered-order dataset. Sparse launch months are flagged in Operational_Note.
A3: Month | B3: Delivered_Orders | C3: On_Time_Orders | D3: Delayed_Orders | E3: Delay_Rate | F3: Avg_Delivery_Days | G3: Avg_Delay_Days | H3: Avg_Review_Score | I3: Avg_Freight | J3: Avg_Items | K3: Operational_Note
A4: 2016-09 | B4: 1 | C4: 0 | D4: 1 | E4: =IFERROR(D4/B4,0) -> 1 | F4: 54.813194 | G4: 36.324745 | H4: 1 | I4: 8.49 | J4: 3 | K4: Low-volume launch month, interpret carefully
A5: 2016-10 | B5: 265 | C5: 262 | D5: 3 | E5: =IFERROR(D5/B5,0) -> 0.011320755 | F5: 19.600559 | G5: 0.078614867 | H5: 4.0114504 | I5: 23.266226 | J5: 1.1811321 | K5: Stable on-time performance
A6: 2016-12 | B6: 1 | C6: 1 | D6: 0 | E6: =IFERROR(D6/B6,0) -> 0 | F6: 4.6930208 | G6: 0 | H6: 5 | I6: 8.72 | J6: 1 | K6: Low-volume launch month, interpret carefully
A7: 2017-01 | B7: 750 | C7: 727 | D7: 23 | E7: =IFERROR(D7/B7,0) -> 0.030666667 | F7: 12.647044 | G7: 0.6086929 | H7: 4.1990553 | I7: 20.912013 | J7: 1.2173333 | K7: Stable on-time performance
A8: 2017-02 | B8: 1653 | C8: 1600 | D8: 53 | E8: =IFERROR(D8/B8,0) -> 0.032062916 | F8: 13.168825 | G8: 0.63256765 | H8: 4.202678 | I8: 22.393176 | J8: 1.1240169 | K8: Stable on-time performance
A9: 2017-03 | B9: 2546 | C9: 2404 | D9: 142 | E9: =IFERROR(D9/B9,0) -> 0.055773763 | F9: 12.951184 | G9: 1.1892369 | H9: 4.1873763 | I9: 21.654399 | J9: 1.1378633 | K9: Monitor trend
A10: 2017-04 | B10: 2303 | C10: 2122 | D10: 181 | E10: =IFERROR(D10/B10,0) -> 0.078593139 | F10: 14.917913 | G10: 0.8499348 | H10: 4.1375546 | I10: 21.772783 | J10: 1.1155015 | K10: Monitor trend
A11: 2017-05 | B11: 3545 | C11: 3417 | D11: 128 | E11: =IFERROR(D11/B11,0) -> 0.036107193 | F11: 11.322363 | G11: 0.39475199 | H11: 4.2382713 | I11: 21.861255 | J11: 1.1291961 | K11: Stable on-time performance
A12: 2017-06 | B12: 3135 | C12: 3014 | D12: 121 | E12: =IFERROR(D12/B12,0) -> 0.038596491 | F12: 12.011573 | G12: 0.45832311 | H12: 4.2229187 | I12: 21.7311 | J12: 1.1129187 | K12: Stable on-time performance
A13: 2017-07 | B13: 3872 | C13: 3739 | D13: 133 | E13: =IFERROR(D13/B13,0) -> 0.034349174 | F13: 11.592732 | G13: 0.35109563 | H13: 4.2584158 | I13: 21.873595 | J13: 1.1404959 | K13: Stable on-time performance
A14: 2017-08 | B14: 4193 | C14: 4054 | D14: 139 | E14: =IFERROR(D14/B14,0) -> 0.033150489 | F14: 11.147125 | G14: 0.27933835 | H14: 4.3115246 | I14: 21.734477 | J14: 1.1440496 | K14: Stable on-time performance
A15: 2017-09 | B15: 4150 | C15: 3934 | D15: 216 | E15: =IFERROR(D15/B15,0) -> 0.052048193 | F15: 11.851007 | G15: 0.45017719 | H15: 4.2674842 | I15: 22.572969 | J15: 1.1414458 | K15: Monitor trend
... A26: 2018-08 | B26: 6351 | C26: 5691 | D26: 660 | E26: =IFERROR(D26/B26,0) -> 0.10392064 | F26: 7.7327797 | G26: 0.34108024 | H26: 4.3103476 | I26: 23.132578 | J26: 1.1245473 | K26: Delay spike: investigate capacity/carrier issues

Sheet State_Analysis
A1: State-Level Delay Hotspots
A2: Top 15 states ranked by delayed order count, with priority based on delay rate and volume.
A3: State | B3: Delivered_Orders | C3: On_Time_Orders | D3: Delayed_Orders | E3: Delay_Rate | F3: Avg_Delivery_Days | G3: Avg_Delay_Days | H3: Avg_Review_Score | I3: Avg_Freight | J3: Priority | K3: Recommended_Action
A4: SP | B4: 40494 | C4: 38107 | D4: 2387 | E4: =IFERROR(D4/B4,0) -> 0.058947004 | F4: 8.761386 | G4: 0.41426975 | H4: 4.246519 | I4: 17.334797 | J4: High | K4: Review carrier SLAs and escalation rules
A5: RJ | B5: 12350 | C5: 10686 | D5: 1664 | E5: =IFERROR(D5/B5,0) -> 0.13473684 | F5: 15.309438 | G5: 1.7311922 | H5: 3.9651407 | I5: 23.947404 | J5: High | K5: Review carrier SLAs and escalation rules
A6: MG | B6: 11354 | C6: 10717 | D6: 637 | E6: =IFERROR(D6/B6,0) -> 0.056103576 | F6: 12.008666 | G6: 0.42235072 | H6: 4.1924679 | I6: 23.463963 | J6: High | K6: Review carrier SLAs and escalation rules
A7: BA | B7: 3256 | C7: 2799 | D7: 457 | E7: =IFERROR(D7/B7,0) -> 0.14035627 | F7: 19.335466 | G7: 1.5578454 | H7: 3.9300093 | I7: 29.961201 | J7: High | K7: Review carrier SLAs and escalation rules
A8: RS | B8: 5344 | C8: 4962 | D8: 382 | E8: =IFERROR(D8/B8,0) -> 0.071482036 | F8: 15.300276 | G8: 0.67247095 | H8: 4.1855989 | I8: 24.805449 | J8: Medium | K8: Monitor weekly and check peak periods
A9: SC | B9: 3546 | C9: 3200 | D9: 346 | E9: =IFERROR(D9/B9,0) -> 0.097574732 | F9: 14.954783 | G9: 0.75136649 | H9: 4.1332765 | I9: 24.849309 | J9: Medium | K9: Monitor weekly and check peak periods
A10: PR | B10: 4923 | C10: 4677 | D10: 246 | E10: =IFERROR(D10/B10,0) -> 0.049969531 | F10: 11.991582 | G10: 0.36977923 | H10: 4.2395918 | I10: 23.490817 | J10: Low | K10: Maintain current process
A11: ES | B11: 1995 | C11: 1751 | D11: 244 | E11: =IFERROR(D11/B11,0) -> 0.12230576 | F11: 15.789307 | G11: 1.2959719 | H11: 4.0797359 | I11: 24.568662 | J11: High | K11: Review carrier SLAs and escalation rules
A12: CE | B12: 1279 | C12: 1083 | D12: 196 | E12: =IFERROR(D12/B12,0) -> 0.15324472 | F12: 21.266579 | G12: 2.1955046 | H12: 3.9418696 | I12: 36.496787 | J12: High | K12: Review carrier SLAs and escalation rules
A13: PE | B13: 1593 | C13: 1421 | D13: 172 | E13: =IFERROR(D13/B13,0) -> 0.10797238 | F13: 18.448323 | G13: 1.2248001 | H13: 4.0829639 | I13: 35.833371 | J13: High | K13: Review carrier SLAs and escalation rules
A14: GO | B14: 1957 | C14: 1797 | D14: 160 | E14: =IFERROR(D14/B14,0) -> 0.081757793 | F14: 15.606339 | G14: 0.80026352 | H14: 4.1043165 | I14: 26.252248 | J14: Medium | K14: Monitor weekly and check peak periods
A15: DF | B15: 2080 | C15: 1933 | D15: 147 | E15: =IFERROR(D15/B15,0) -> 0.070673077 | F15: 12.967568 | G15: 0.46918566 | H15: 4.1338164 | I15: 23.858144 | J15: Medium | K15: Monitor weekly and check peak periods
... A18: AL | B18: 397 | C18: 302 | D18: 95 | E18: =IFERROR(D18/B18,0) -> 0.23929471 | F18: 24.543855 | G18: 2.2125499 | H18: 3.8527919 | I18: 38.581285 | J18: High | K18: Review carrier SLAs and escalation rules

Sheet Category_Analysis
A1: Product Category Delay Risk Analysis
A2: Top 15 product categories among categories with at least 200 delivered orders, ranked by delay rate.
A3: Category | B3: Delivered_Orders | C3: On_Time_Orders | D3: Delayed_Orders | E3: Delay_Rate | F3: Avg_Delivery_Days | G3: Avg_Delay_Days | H3: Avg_Review_Score | I3: Avg_Freight | J3: Priority | K3: Recommended_Action
A4: Audio | B4: 344 | C4: 299 | D4: 45 | E4: =IFERROR(D4/B4,0) -> 0.13081395 | F4: 13.506538 | G4: 1.0908512 | H4: 3.8460411 | I4: 16.441773 | J4: High | K4: Audit category packaging, supplier readiness, and carrier handoff
A5: Books Technical | B5: 255 | C5: 227 | D5: 28 | E5: =IFERROR(D5/B5,0) -> 0.10980392 | F5: 10.644328 | G5: 0.60594485 | H5: 4.4251969 | I5: 16.607216 | J5: High | K5: Audit category packaging, supplier readiness, and carrier handoff
A6: Home Confort | B6: 367 | C6: 329 | D6: 38 | E6: =IFERROR(D6/B6,0) -> 0.10354223 | F6: 13.576062 | G6: 1.3681457 | H6: 3.909589 | I6: 23.226131 | J6: High | K6: Audit category packaging, supplier readiness, and carrier handoff
A7: Food | B7: 436 | C7: 392 | D7: 44 | E7: =IFERROR(D7/B7,0) -> 0.10091743 | F7: 9.8160277 | G7: 1.0577255 | H7: 4.3240741 | I7: 16.114908 | J7: High | K7: Audit category packaging, supplier readiness, and carrier handoff
A8: Electronics | B8: 2507 | C8: 2260 | D8: 247 | E8: =IFERROR(D8/B8,0) -> 0.098524132 | F8: 12.936072 | G8: 0.78279142 | H8: 4.1290193 | I8: 18.351005 | J8: Medium | K8: Monitor during high-volume weeks
A9: Baby | B9: 2764 | C9: 2506 | D9: 258 | E9: =IFERROR(D9/B9,0) -> 0.093342981 | F9: 12.731318 | G9: 0.99874722 | H9: 4.1208972 | I9: 24.031422 | J9: Medium | K9: Monitor during high-volume weeks
A10: Office Furniture | B10: 1246 | C10: 1131 | D10: 115 | E10: =IFERROR(D10/B10,0) -> 0.092295345 | F10: 20.702587 | G10: 1.1346767 | H10: 3.6500809 | I10: 53.578483 | J10: Medium | K10: Monitor during high-volume weeks
A11: Construction Tools Construction | B11: 727 | C11: 660 | D11: 67 | E11: =IFERROR(D11/B11,0) -> 0.09215956 | F11: 10.86961 | G11: 0.95266161 | H11: 4.1308864 | I11: 28.01414 | J11: Medium | K11: Monitor during high-volume weeks
A12: Construction Tools Lights | B12: 232 | C12: 211 | D12: 21 | E12: =IFERROR(D12/B12,0) -> 0.090517241 | F12: 9.7490544 | G12: 0.4638633 | H12: 4.2008734 | I12: 32.097759 | J12: Medium | K12: Monitor during high-volume weeks
A13: Health Beauty | B13: 8610 | C13: 7836 | D13: 774 | E13: =IFERROR(D13/B13,0) -> 0.08989547 | F13: 12.098038 | G13: 0.80372171 | H13: 4.2353846 | I13: 20.779994 | J13: Medium | K13: Monitor during high-volume weeks
A14: Unknown | B14: 1355 | C14: 1234 | D14: 121 | E14: =IFERROR(D14/B14,0) -> 0.089298893 | F14: 12.749703 | G14: 0.81584978 | H14: 4.0375186 | I14: 19.461506 | J14: Medium | K14: Monitor during high-volume weeks
A15: Musical Instruments | B15: 608 | C15: 554 | D15: 54 | E15: =IFERROR(D15/B15,0) -> 0.088815789 | F15: 13.115038 | G15: 0.99946251 | H15: 4.2425249 | I15: 29.498882 | J15: Medium | K15: Monitor during high-volume weeks
... A18: Furniture Living Room | B18: 409 | C18: 374 | D18: 35 | E18: =IFERROR(D18/B18,0) -> 0.085574572 | F18: 13.945042 | G18: 0.86609934 | H18: 4.0940594 | I18: 43.642152 | J18: Medium | K18: Monitor during high-volume weeks

Sheet Data_Source_Methodology
A1: Data Source and Methodology
A3: Section | B3: Details
A4: Project objective | B4: Analyze operational delivery performance using public e-commerce data, identify delay patterns, and recommend practical process improvements.
A5: Primary public dataset | B5: Olist Brazilian E-Commerce Public Dataset by Olist. The dataset contains anonymized e-commerce orders from Brazil across orders, items, customers, products, reviews, payments, sellers, and geolocation tables.
A6: Source URL | B6: https://www.kaggle.com/datasets/olistbr/brazilian-ecommerce
A7: GitHub mirror used for CSV access | B7: https://github.com/Ganesh7699/Brazilian-E-Commerce-OList
A8: Tables used | B8: olist_orders_dataset.csv, olist_customers_dataset.csv, olist_order_items_dataset.csv, olist_order_reviews_dataset.csv, olist_products_dataset.csv, product_category_name_translation.csv
A9: Data cleaning steps | B9: Filtered delivered orders with valid purchase, estimated delivery, and actual delivery dates; joined customers for location; joined order items for product value, freight, item count, and category; joined reviews for review score; translated product categories into English.
A10: KPI definitions | B10: Delay Days = max(0, Delivered Date - Estimated Date). Delay Rate = Delayed Orders / Delivered Orders. Delivery Days = Delivered Date - Purchase Date. On-Time Orders = delivered on or before estimated date.
A11: Analysis methods | B11: Monthly trend analysis, state-level delay hotspot analysis, category risk analysis, delivery duration calculations, SLA bucket classification, review-score comparison, and chart-based dashboarding.
A12: Interpretation note | B12: Raw_Data_Sample contains a representative sample of 2,000 joined delivered orders for transparency and editable formulas. The summary analysis tables were calculated from the full delivered-order dataset.
A13: Recommended tools | B13: Excel or Google Sheets for filtering, formulas, charts, and dashboard review. Power BI can also be used if a more interactive version is needed.

Sheet Recommendations
A1: Operational Recommendations and Action Plan
A3: Priority | B3: Recommendation | C3: Evidence | D3: Expected Operational Benefit | E3: Owner | F3: Suggested KPI | G3: Timeframe | H3: Status
A4: High | B4: Create a weekly delivery delay dashboard by state. | C4: RJ and BA show higher delay rates than the overall average. | D4: Faster visibility of late delivery risk and better escalation before customer complaints. | E4: Operations Analyst / Logistics Lead | F4: Delay Rate by State | G4: 2 weeks | H4: Ready
A5: High | B5: Introduce exception alerts for orders at risk of missing estimated delivery dates. | C5: Delayed orders are concentrated in specific periods and regions. | D5: Reduces reactive follow-up and improves customer communication. | E5: Operations Specialist | F5: Orders At Risk | G5: 2-4 weeks | H5: Ready
A6: Medium | B6: Review carrier SLA performance in high-delay states. | C6: States with higher average delivery days also show higher delay rates. | D6: Better route planning, carrier accountability, and escalation. | E6: Logistics Coordinator | F6: Carrier On-Time Rate | G6: 1 month | H6: Ready
A7: Medium | B7: Audit categories with high delay rates for packaging and handling complexity. | C7: Audio, Home Comfort, Food, and Electronics have elevated delay rates in this analysis. | D7: Reduces category-specific bottlenecks and improves fulfillment consistency. | E7: Warehouse / Fulfillment Team | F7: Category Delay Rate | G7: 1 month | H7: Ready
A8: Medium | B8: Track customer review score beside delivery KPIs. | C8: Review scores are a useful customer experience signal after delivery. | D8: Connects operational performance with customer satisfaction outcomes. | E8: Customer Success + Operations | F8: Review Score by Delay Status | G8: 2 weeks | H8: Ready
A9: Low | B9: Standardize a monthly operations report template. | C9: Monthly delay rates show useful trends for decision-making. | D9: Creates repeatable reporting and supports better management communication. | E9: Operations Assistant | F9: Monthly KPI Completion | G9: Ongoing | H9: Ready
