Workbook

Sheet Dashboard
A1: Week 4: Operational Inventory and Resource Optimization
A2: Scenario: E-commerce fulfillment center using moving-average forecasting, reorder points, safety stock and resource planning.
A4: KPI | B4: Value | C4: Interpretation | D4: Action
A5: Jan Forecast Demand | B5: 8277 | C5: Expected units required next month | D5: Plan purchasing and warehouse capacity
A6: Current Stock | B6: 12200 | C6: Units currently available | D6: Compare with forecast and reorder point
A7: On Order | B7: 2950 | C7: Units already committed from suppliers | D7: Track supplier delivery dates
A8: Recommended Order Qty | B8: 1331 | C8: Suggested purchase quantity | D8: Prioritize high-risk categories
A9: High Stockout Risk Categories | B9: 0 | C9: Categories below reorder point | D9: Escalate immediately
A10: High Overstock Risk Categories | B10: 1 | C10: Categories with excess inventory | D10: Promotion or purchasing freeze
A11: Average Supplier Lead Time | B11: 12.4 | C11: Average days to replenish | D11: Monitor supplier reliability
A14: Month | B14: Jan-25 | C14: Feb-25 | D14: Mar-25 | E14: Apr-25 | F14: May-25 | G14: Jun-25 | H14: Jul-25 | I14: Aug-25 | J14: Sep-25 | K14: Oct-25 | L14: Nov-25 | M14: Dec-25 | N14: Jan-26 | O14: Feb-26 | P14: Mar-26
A15: Total Demand | B15: 4480 | C15: 4620 | D15: 4900 | E15: 5210 | F15: 5620 | G15: 6050 | H15: 6410 | I15: 6780 | J15: 7100 | K15: 7550 | L15: 8665 | M15: 10310 | N15: 8277 | O15: 8931 | P15: 9588
A18: Category | B18: Current Stock | C18: Reorder Point | D18: Recommended Order Qty | F18: Risk Level | G18: Count
A19: Consumer Electronics | B19: 2700 | C19: 975 | D19: 0 | F19: High | G19: 0
A20: Beauty & Personal Care | B20: 1650 | C20: 600 | D20: 133 | F20: Medium | G20: 1
A21: Home & Kitchen | B21: 1500 | C21: 632 | D21: 16 | F21: Low | G21: 7
A22: Fashion Accessories | B22: 1200 | C22: 980 | D22: 436
A23: Health & Wellness | B23: 1150 | C23: 433 | D23: 229
A24: Toys & Games | B24: 900 | C24: 857 | D24: 517
A25: Office Supplies | B25: 1300 | C25: 236 | D25: 0
A26: Sports & Outdoor | B26: 1800 | C26: 430 | D26: 0

Sheet Assumptions
A1: Inventory Optimization Assumptions and Methodology
A3: Input / Method | B3: Value | D3: Formula | E3: Use in workbook
A4: Scenario | B4: E-commerce fulfillment operation managing multi-category inventory and warehouse resources | D4: 3-Month Moving Average | E4: Average of the last three demand periods to smooth short-term fluctuation.
A5: Forecasting method | B5: 3-month moving average with category-specific seasonal adjustment | D5: Seasonal Forecast | E5: Moving average multiplied by seasonal adjustment factor for the next month.
A6: Planning horizon | B6: January to March 2026 | D6: Safety Stock | E6: Historical demand variation adjusted by supplier lead time and service factor.
A7: Demand unit | B7: Order units by product category | D7: Reorder Point | E7: Expected demand during lead time plus safety stock.
A8: Service level target | B8: 95% availability for A and B priority categories | D8: Recommended Order Quantity | E8: Target coverage requirement minus inventory position, constrained to zero minimum.
A9: Safety stock factor | B9: 1.65
A10: Target coverage days | B10: 45
A11: Warehouse working days per month | B11: 22
A12: Pick/pack productivity | B12: 85 order units per associate per day
A13: Receiving productivity | B13: 220 units per receiving associate per day
A14: Customer service planning | B14: 1 agent per 550 forecasted service tickets
A15: Source | B15: Simulated operational dataset built from realistic e-commerce fulfillment assumptions for this Week 4 task

Sheet Demand History
A1: Category | B1: Jan-25 | C1: Feb-25 | D1: Mar-25 | E1: Apr-25 | F1: May-25 | G1: Jun-25 | H1: Jul-25 | I1: Aug-25 | J1: Sep-25 | K1: Oct-25 | L1: Nov-25 | M1: Dec-25 | N1: Total Actual Demand | O1: Average Monthly Demand
A2: Consumer Electronics | B2: 980 | C2: 910 | D2: 950 | E2: 1020 | F2: 1100 | G2: 1180 | H2: 1210 | I2: 1260 | J2: 1320 | K2: 1420 | L2: 1680 | M2: 1890 | N2: 14920 | O2: 1243.3
A3: Beauty & Personal Care | B3: 740 | C3: 780 | D3: 820 | E3: 860 | F3: 920 | G3: 990 | H3: 1040 | I3: 1090 | J3: 1150 | K3: 1220 | L3: 1325 | M3: 1550 | N3: 12485 | O3: 1040.4
A4: Home & Kitchen | B4: 650 | C4: 680 | D4: 720 | E4: 740 | F4: 780 | G4: 810 | H4: 850 | I4: 880 | J4: 920 | K4: 980 | L4: 1120 | M4: 1380 | N4: 10510 | O4: 875.8
A5: Fashion Accessories | B5: 520 | C5: 560 | D5: 590 | E5: 620 | F5: 680 | G5: 720 | H5: 760 | I5: 810 | J5: 870 | K5: 940 | L5: 1180 | M5: 1600 | N5: 9850 | O5: 820.8
A6: Health & Wellness | B6: 460 | C6: 480 | D6: 510 | E6: 540 | F6: 600 | G6: 640 | H6: 690 | I6: 720 | J6: 760 | K6: 810 | L6: 920 | M6: 1080 | N6: 8210 | O6: 684.2
A7: Toys & Games | B7: 310 | C7: 330 | D7: 350 | E7: 380 | F7: 400 | G7: 450 | H7: 480 | I7: 520 | J7: 590 | K7: 720 | L7: 980 | M7: 1350 | N7: 6860 | O7: 571.7
A8: Office Supplies | B8: 390 | C8: 410 | D8: 440 | E8: 470 | F8: 500 | G8: 530 | H8: 560 | I8: 600 | J8: 640 | K8: 680 | L8: 720 | M8: 760 | N8: 6700 | O8: 558.3
A9: Sports & Outdoor | B9: 430 | C9: 470 | D9: 520 | E9: 580 | F9: 640 | G9: 730 | H9: 820 | I9: 900 | J9: 850 | K9: 780 | L9: 740 | M9: 700 | N9: 8160 | O9: 680

Sheet Forecast Model
A1: Category | B1: Jan-25 | C1: Feb-25 | D1: Mar-25 | E1: Apr-25 | F1: May-25 | G1: Jun-25 | H1: Jul-25 | I1: Aug-25 | J1: Sep-25 | K1: Oct-25 | L1: Nov-25 | M1: Dec-25 | N1: 3-Month Avg | O1: Jan Seasonality | P1: Jan-26 Forecast | Q1: Feb Seasonality | R1: Feb-26 Forecast | S1: Mar Seasonality | T1: Mar-26 Forecast
A2: Consumer Electronics | B2: 980 | C2: 910 | D2: 950 | E2: 1020 | F2: 1100 | G2: 1180 | H2: 1210 | I2: 1260 | J2: 1320 | K2: 1420 | L2: 1680 | M2: 1890 | N2: =AVERAGE(K2:M2) -> 1663.3333 | O2: 0.88 | P2: =ROUND(N2*O2,0) -> 1464 | Q2: 0.98 | R2: =ROUND(AVERAGE(L2,M2,P2)*Q2,0) -> 1644 | S2: 1.05 | T2: =ROUND(AVERAGE(M2,P2,R2)*S2,0) -> 1749
A3: Beauty & Personal Care | B3: 740 | C3: 780 | D3: 820 | E3: 860 | F3: 920 | G3: 990 | H3: 1040 | I3: 1090 | J3: 1150 | K3: 1220 | L3: 1325 | M3: 1550 | N3: =AVERAGE(K3:M3) -> 1365 | O3: 0.95 | P3: =ROUND(N3*O3,0) -> 1297 | Q3: 1 | R3: =ROUND(AVERAGE(L3,M3,P3)*Q3,0) -> 1391 | S3: 1.03 | T3: =ROUND(AVERAGE(M3,P3,R3)*S3,0) -> 1455
A4: Home & Kitchen | B4: 650 | C4: 680 | D4: 720 | E4: 740 | F4: 780 | G4: 810 | H4: 850 | I4: 880 | J4: 920 | K4: 980 | L4: 1120 | M4: 1380 | N4: =AVERAGE(K4:M4) -> 1160 | O4: 0.9 | P4: =ROUND(N4*O4,0) -> 1044 | Q4: 0.98 | R4: =ROUND(AVERAGE(L4,M4,P4)*Q4,0) -> 1158 | S4: 1.08 | T4: =ROUND(AVERAGE(M4,P4,R4)*S4,0) -> 1290
A5: Fashion Accessories | B5: 520 | C5: 560 | D5: 590 | E5: 620 | F5: 680 | G5: 720 | H5: 760 | I5: 810 | J5: 870 | K5: 940 | L5: 1180 | M5: 1600 | N5: =AVERAGE(K5:M5) -> 1240 | O5: 0.88 | P5: =ROUND(N5*O5,0) -> 1091 | Q5: 0.95 | R5: =ROUND(AVERAGE(L5,M5,P5)*Q5,0) -> 1226 | S5: 1.06 | T5: =ROUND(AVERAGE(M5,P5,R5)*S5,0) -> 1384
A6: Health & Wellness | B6: 460 | C6: 480 | D6: 510 | E6: 540 | F6: 600 | G6: 640 | H6: 690 | I6: 720 | J6: 760 | K6: 810 | L6: 920 | M6: 1080 | N6: =AVERAGE(K6:M6) -> 936.66667 | O6: 1.08 | P6: =ROUND(N6*O6,0) -> 1012 | Q6: 1.05 | R6: =ROUND(AVERAGE(L6,M6,P6)*Q6,0) -> 1054 | S6: 1.06 | T6: =ROUND(AVERAGE(M6,P6,R6)*S6,0) -> 1112
A7: Toys & Games | B7: 310 | C7: 330 | D7: 350 | E7: 380 | F7: 400 | G7: 450 | H7: 480 | I7: 520 | J7: 590 | K7: 720 | L7: 980 | M7: 1350 | N7: =AVERAGE(K7:M7) -> 1016.6667 | O7: 0.7 | P7: =ROUND(N7*O7,0) -> 712 | Q7: 0.86 | R7: =ROUND(AVERAGE(L7,M7,P7)*Q7,0) -> 872 | S7: 0.95 | T7: =ROUND(AVERAGE(M7,P7,R7)*S7,0) -> 929
A8: Office Supplies | B8: 390 | C8: 410 | D8: 440 | E8: 470 | F8: 500 | G8: 530 | H8: 560 | I8: 600 | J8: 640 | K8: 680 | L8: 720 | M8: 760 | N8: =AVERAGE(K8:M8) -> 720 | O8: 1.15 | P8: =ROUND(N8*O8,0) -> 828 | Q8: 1 | R8: =ROUND(AVERAGE(L8,M8,P8)*Q8,0) -> 769 | S8: 0.98 | T8: =ROUND(AVERAGE(M8,P8,R8)*S8,0) -> 770
A9: Sports & Outdoor | B9: 430 | C9: 470 | D9: 520 | E9: 580 | F9: 640 | G9: 730 | H9: 820 | I9: 900 | J9: 850 | K9: 780 | L9: 740 | M9: 700 | N9: =AVERAGE(K9:M9) -> 740 | O9: 1.12 | P9: =ROUND(N9*O9,0) -> 829 | Q9: 1.08 | R9: =ROUND(AVERAGE(L9,M9,P9)*Q9,0) -> 817 | S9: 1.15 | T9: =ROUND(AVERAGE(M9,P9,R9)*S9,0) -> 899
A10: Total | B10: =SUM(B2:B9) -> 4480 | C10: =SUM(C2:C9) -> 4620 | D10: =SUM(D2:D9) -> 4900 | E10: =SUM(E2:E9) -> 5210 | F10: =SUM(F2:F9) -> 5620 | G10: =SUM(G2:G9) -> 6050 | H10: =SUM(H2:H9) -> 6410 | I10: =SUM(I2:I9) -> 6780 | ... N10: =SUM(N2:N9) -> 8841.6667 | P10: =SUM(P2:P9) -> 8277 | R10: =SUM(R2:R9) -> 8931 | T10: =SUM(T2:T9) -> 9588

Sheet Reorder Plan
A1: Category | B1: ABC Class | C1: Supplier Lead Time (days) | D1: Current Stock | E1: On Order | F1: Jan-26 Forecast | G1: Feb-26 Forecast | H1: Mar-26 Forecast | I1: Daily Demand | J1: Safety Stock | K1: Reorder Point | L1: Inventory Position | M1: Recommended Order Qty | N1: Projected Ending Stock | O1: Stockout Risk | P1: Overstock Risk | Q1: Priority | R1: Unit Cost | S1: Estimated Purchase Cost
A2: Consumer Electronics | B2: A | C2: 14 | D2: 2700 | E2: 600 | F2: ='Forecast Model'!P2 -> 1464 | G2: ='Forecast Model'!R2 -> 1644 | H2: ='Forecast Model'!T2 -> 1749 | I2: =F2/30 -> 48.8 | J2: =ROUNDUP(_xludf.STDEV.S('Forecast Model'!J2:M2)*SQRT(C2/30)*Assumptions!$B$9,0) -> #NAME? | K2: =ROUNDUP(I2*C2+J2,0) -> #NAME? | L2: =D2+E2 -> 3300 | M2: =MAX(0,ROUNDUP(((F2+G2)*Assumptions!$B$10/60+J2)-L2,0)) -> #NAME? | N2: =L2-F2 -> 1836 | O2: =IF(L2<K2,"High",IF(N2<J2,"Medium","Low")) -> #NAME? | P2: =IF(L2>(F2+G2+J2)*1.25,"High",IF(L2>(F2+G2+J2)*1.05,"Medium","Low")) -> #NAME? | Q2: =IF(O2="High","Immediate reorder",IF(O2="Medium","Review within 1 week",IF(P2="High","Reduce / promote","Monitor"))) -> #NAME? | R2: 110 | S2: =M2*R2 -> #NAME?
A3: Beauty & Personal Care | B3: A | C3: 10 | D3: 1650 | E3: 400 | F3: ='Forecast Model'!P3 -> 1297 | G3: ='Forecast Model'!R3 -> 1391 | H3: ='Forecast Model'!T3 -> 1455 | I3: =F3/30 -> 43.233333 | J3: =ROUNDUP(_xludf.STDEV.S('Forecast Model'!J3:M3)*SQRT(C3/30)*Assumptions!$B$9,0) -> #NAME? | K3: =ROUNDUP(I3*C3+J3,0) -> #NAME? | L3: =D3+E3 -> 2050 | M3: =MAX(0,ROUNDUP(((F3+G3)*Assumptions!$B$10/60+J3)-L3,0)) -> #NAME? | N3: =L3-F3 -> 753 | O3: =IF(L3<K3,"High",IF(N3<J3,"Medium","Low")) -> #NAME? | P3: =IF(L3>(F3+G3+J3)*1.25,"High",IF(L3>(F3+G3+J3)*1.05,"Medium","Low")) -> #NAME? | Q3: =IF(O3="High","Immediate reorder",IF(O3="Medium","Review within 1 week",IF(P3="High","Reduce / promote","Monitor"))) -> #NAME? | R3: 22 | S3: =M3*R3 -> #NAME?
A4: Home & Kitchen | B4: B | C4: 12 | D4: 1500 | E4: 350 | F4: ='Forecast Model'!P4 -> 1044 | G4: ='Forecast Model'!R4 -> 1158 | H4: ='Forecast Model'!T4 -> 1290 | I4: =F4/30 -> 34.8 | J4: =ROUNDUP(_xludf.STDEV.S('Forecast Model'!J4:M4)*SQRT(C4/30)*Assumptions!$B$9,0) -> #NAME? | K4: =ROUNDUP(I4*C4+J4,0) -> #NAME? | L4: =D4+E4 -> 1850 | M4: =MAX(0,ROUNDUP(((F4+G4)*Assumptions!$B$10/60+J4)-L4,0)) -> #NAME? | N4: =L4-F4 -> 806 | O4: =IF(L4<K4,"High",IF(N4<J4,"Medium","Low")) -> #NAME? | P4: =IF(L4>(F4+G4+J4)*1.25,"High",IF(L4>(F4+G4+J4)*1.05,"Medium","Low")) -> #NAME? | Q4: =IF(O4="High","Immediate reorder",IF(O4="Medium","Review within 1 week",IF(P4="High","Reduce / promote","Monitor"))) -> #NAME? | R4: 38 | S4: =M4*R4 -> #NAME?
A5: Fashion Accessories | B5: B | C5: 16 | D5: 1200 | E5: 500 | F5: ='Forecast Model'!P5 -> 1091 | G5: ='Forecast Model'!R5 -> 1226 | H5: ='Forecast Model'!T5 -> 1384 | I5: =F5/30 -> 36.366667 | J5: =ROUNDUP(_xludf.STDEV.S('Forecast Model'!J5:M5)*SQRT(C5/30)*Assumptions!$B$9,0) -> #NAME? | K5: =ROUNDUP(I5*C5+J5,0) -> #NAME? | L5: =D5+E5 -> 1700 | M5: =MAX(0,ROUNDUP(((F5+G5)*Assumptions!$B$10/60+J5)-L5,0)) -> #NAME? | N5: =L5-F5 -> 609 | O5: =IF(L5<K5,"High",IF(N5<J5,"Medium","Low")) -> #NAME? | P5: =IF(L5>(F5+G5+J5)*1.25,"High",IF(L5>(F5+G5+J5)*1.05,"Medium","Low")) -> #NAME? | Q5: =IF(O5="High","Immediate reorder",IF(O5="Medium","Review within 1 week",IF(P5="High","Reduce / promote","Monitor"))) -> #NAME? | R5: 18 | S5: =M5*R5 -> #NAME?
A6: Health & Wellness | B6: B | C6: 9 | D6: 1150 | E6: 300 | F6: ='Forecast Model'!P6 -> 1012 | G6: ='Forecast Model'!R6 -> 1054 | H6: ='Forecast Model'!T6 -> 1112 | I6: =F6/30 -> 33.733333 | J6: =ROUNDUP(_xludf.STDEV.S('Forecast Model'!J6:M6)*SQRT(C6/30)*Assumptions!$B$9,0) -> #NAME? | K6: =ROUNDUP(I6*C6+J6,0) -> #NAME? | L6: =D6+E6 -> 1450 | M6: =MAX(0,ROUNDUP(((F6+G6)*Assumptions!$B$10/60+J6)-L6,0)) -> #NAME? | N6: =L6-F6 -> 438 | O6: =IF(L6<K6,"High",IF(N6<J6,"Medium","Low")) -> #NAME? | P6: =IF(L6>(F6+G6+J6)*1.25,"High",IF(L6>(F6+G6+J6)*1.05,"Medium","Low")) -> #NAME? | Q6: =IF(O6="High","Immediate reorder",IF(O6="Medium","Review within 1 week",IF(P6="High","Reduce / promote","Monitor"))) -> #NAME? | R6: 28 | S6: =M6*R6 -> #NAME?
A7: Toys & Games | B7: C | C7: 18 | D7: 900 | E7: 200 | F7: ='Forecast Model'!P7 -> 712 | G7: ='Forecast Model'!R7 -> 872 | H7: ='Forecast Model'!T7 -> 929 | I7: =F7/30 -> 23.733333 | J7: =ROUNDUP(_xludf.STDEV.S('Forecast Model'!J7:M7)*SQRT(C7/30)*Assumptions!$B$9,0) -> #NAME? | K7: =ROUNDUP(I7*C7+J7,0) -> #NAME? | L7: =D7+E7 -> 1100 | M7: =MAX(0,ROUNDUP(((F7+G7)*Assumptions!$B$10/60+J7)-L7,0)) -> #NAME? | N7: =L7-F7 -> 388 | O7: =IF(L7<K7,"High",IF(N7<J7,"Medium","Low")) -> #NAME? | P7: =IF(L7>(F7+G7+J7)*1.25,"High",IF(L7>(F7+G7+J7)*1.05,"Medium","Low")) -> #NAME? | Q7: =IF(O7="High","Immediate reorder",IF(O7="Medium","Review within 1 week",IF(P7="High","Reduce / promote","Monitor"))) -> #NAME? | R7: 24 | S7: =M7*R7 -> #NAME?
A8: Office Supplies | B8: C | C8: 7 | D8: 1300 | E8: 250 | F8: ='Forecast Model'!P8 -> 828 | G8: ='Forecast Model'!R8 -> 769 | H8: ='Forecast Model'!T8 -> 770 | I8: =F8/30 -> 27.6 | J8: =ROUNDUP(_xludf.STDEV.S('Forecast Model'!J8:M8)*SQRT(C8/30)*Assumptions!$B$9,0) -> #NAME? | K8: =ROUNDUP(I8*C8+J8,0) -> #NAME? | L8: =D8+E8 -> 1550 | M8: =MAX(0,ROUNDUP(((F8+G8)*Assumptions!$B$10/60+J8)-L8,0)) -> #NAME? | N8: =L8-F8 -> 722 | O8: =IF(L8<K8,"High",IF(N8<J8,"Medium","Low")) -> #NAME? | P8: =IF(L8>(F8+G8+J8)*1.25,"High",IF(L8>(F8+G8+J8)*1.05,"Medium","Low")) -> #NAME? | Q8: =IF(O8="High","Immediate reorder",IF(O8="Medium","Review within 1 week",IF(P8="High","Reduce / promote","Monitor"))) -> #NAME? | R8: 12 | S8: =M8*R8 -> #NAME?
A9: Sports & Outdoor | B9: C | C9: 13 | D9: 1800 | E9: 350 | F9: ='Forecast Model'!P9 -> 829 | G9: ='Forecast Model'!R9 -> 817 | H9: ='Forecast Model'!T9 -> 899 | I9: =F9/30 -> 27.633333 | J9: =ROUNDUP(_xludf.STDEV.S('Forecast Model'!J9:M9)*SQRT(C9/30)*Assumptions!$B$9,0) -> #NAME? | K9: =ROUNDUP(I9*C9+J9,0) -> #NAME? | L9: =D9+E9 -> 2150 | M9: =MAX(0,ROUNDUP(((F9+G9)*Assumptions!$B$10/60+J9)-L9,0)) -> #NAME? | N9: =L9-F9 -> 1321 | O9: =IF(L9<K9,"High",IF(N9<J9,"Medium","Low")) -> #NAME? | P9: =IF(L9>(F9+G9+J9)*1.25,"High",IF(L9>(F9+G9+J9)*1.05,"Medium","Low")) -> #NAME? | Q9: =IF(O9="High","Immediate reorder",IF(O9="Medium","Review within 1 week",IF(P9="High","Reduce / promote","Monitor"))) -> #NAME? | R9: 45 | S9: =M9*R9 -> #NAME?
A10: Total / Summary | D10: =SUM(D2:D9) -> 12200 | E10: =SUM(E2:E9) -> 2950 | F10: =SUM(F2:F9) -> 8277 | G10: =SUM(G2:G9) -> 8931 | H10: =SUM(H2:H9) -> 9588 | J10: =SUM(J2:J9) -> #NAME? | K10: =SUM(K2:K9) -> #NAME? | L10: =SUM(L2:L9) -> 15150 | M10: =SUM(M2:M9) -> #NAME? | N10: =SUM(N2:N9) -> 6873 | S10: =SUM(S2:S9) -> #NAME?

Sheet Resource Plan
A1: Month | B1: Forecasted Units | C1: Expected Customer Service Tickets | D1: Pick/Pack Associates | E1: Receiving Associates | F1: Inventory Control Associates | G1: Customer Service Agents | H1: Resource Notes
A2: Jan-26 | B2: 8277 | C2: 662 | D2: 5 | E2: 1 | F2: 2 | G2: 2 | H2: Maintain baseline coverage
A3: Feb-26 | B3: 8931 | C3: 714 | D3: 5 | E3: 1 | F3: 2 | G3: 2 | H3: Maintain baseline coverage
A4: Mar-26 | B4: 9588 | C4: 767 | D4: 6 | E4: 1 | F4: 2 | G4: 2 | H4: Peak resource level required

Sheet Risk Register
A1: Risk | B1: Impact | C1: Operational Effect | D1: Mitigation Strategy | E1: Owner | F1: Status
A2: Demand spike higher than forecast | B2: High | C2: Stockouts and backorders | D2: Use weekly forecast refresh and keep safety stock for A/B items | E2: Operations Manager | F2: Open
A3: Supplier lead time delays | B3: High | C3: Late replenishment and missed SLAs | D3: Track supplier delivery commitments and create backup supplier list | E3: Procurement Lead | F3: Open
A4: Excess inventory after seasonal peak | B4: Medium | C4: Higher storage cost and working capital pressure | D4: Use markdown plan and freeze buying for slow-moving SKUs | E4: Inventory Controller | F4: Open
A5: Inaccurate inventory counts | B5: High | C5: False availability and customer complaints | D5: Run weekly cycle counts and barcode reconciliation | E5: Warehouse Supervisor | F5: Open
A6: Warehouse labor shortage | B6: Medium | C6: Picking delays during high-volume weeks | D6: Schedule flexible staff based on forecasted demand | E6: Operations Assistant | F6: Open
A7: System update delays | B7: Medium | C7: Late KPI tracking and manual reporting | D7: Use temporary Excel dashboard until automation is ready | E7: Data Analyst | F7: Open

Sheet Recommendations
A1: No. | B1: Recommendation | C1: Action Details | D1: Expected Benefit | E1: Timing
A2: 1 | B2: Set reorder-point alerts | C2: Use the reorder point and safety stock fields to trigger weekly purchasing actions. | D2: Fewer emergency orders and lower stockout risk | E2: Immediate
A3: 2 | B3: Review high-risk categories first | C3: Prioritize categories with High or Medium stockout risk before placing broad orders. | D3: Better use of budget and purchasing capacity | E3: Immediate
A4: 3 | B4: Use weekly rolling forecast | C4: Refresh the 3-month moving average every week using the latest order and inventory data. | D4: More accurate demand planning | E4: 2 weeks
A5: 4 | B5: Reduce overstock through promotions | C5: Apply promotions or purchase freezes to categories with high overstock risk. | D5: Lower storage cost and excess inventory | E5: 2 to 4 weeks
A6: 5 | B6: Align staff schedules with forecast | C6: Plan picking, receiving, and customer service staffing based on monthly forecasted volume. | D6: Faster fulfillment and fewer bottlenecks | E6: Monthly
A7: 6 | B7: Improve supplier visibility | C7: Track lead times, late deliveries, and SLA compliance by supplier. | D7: More reliable replenishment cycle | E7: Monthly
